[
    {
        "urn_id": "ACoAAB5NSQkB5ESUJYjafNH0vNQmPlY6OTi4e9Y",
        "distance": "DISTANCE_2",
        "public_id": "brunaffmarques",
        "tracking_id": "508381449"
    },
    {
        "urn_id": "ACoAAAjpEUEBnkBTlkANoMXBN00-32nEelkb00I",
        "distance": "DISTANCE_2",
        "public_id": "claudia-paiva-71509342",
        "tracking_id": "149492033"
    },
    {
        "urn_id": "ACoAAA-OdDcBOOP_LZjuO2a62YlwO45KbST-xqc",
        "distance": "DISTANCE_2",
        "public_id": "biancaburlim",
        "tracking_id": "260994103"
    },
    {
        "urn_id": "ACoAAA0Z1TkBapXNBVaTJaWSbxWBt91qtaY-3MY",
        "distance": "DISTANCE_2",
        "public_id": "mariana-krüger-she-her-ela-dela-27573961",
        "tracking_id": "219796793"
    },
    {
        "urn_id": "ACoAAAYxQKIBSf84xwbv_tz3GhTcQmZJLu7laIA",
        "distance": "DISTANCE_2",
        "public_id": "everly-marchesini-2029622a",
        "tracking_id": "103891106"
    },
    {
        "urn_id": "ACoAAAyJu1MB0jUO9h_DBHOrxEm0c_S7SM8W1Tc",
        "distance": "DISTANCE_2",
        "public_id": "victornagamine",
        "tracking_id": "210352979"
    },
    {
        "urn_id": "ACoAAByOEKABEEP6xSl6-FQDqNCfLLcB5R6ZK70",
        "distance": "DISTANCE_2",
        "public_id": "nathalia-aranda-ferreira",
        "tracking_id": "479072416"
    },
    {
        "urn_id": "ACoAAAZYwiQBA_kIzHSJP1qLb8DVXNmr6NE1gK8",
        "distance": "DISTANCE_2",
        "public_id": "nara-zarino",
        "tracking_id": "106480164"
    },
    {
        "urn_id": "ACoAAALk9PsBe31QjfZc9BjuVkNdTUSJpsdF1Lw",
        "distance": "DISTANCE_2",
        "public_id": "marcelomalcher",
        "tracking_id": "48559355"
    },
    {
        "urn_id": "ACoAAAotUv8BYp20hwIpZ5m860jsWfljzmj67kI",
        "distance": "DISTANCE_2",
        "public_id": "alinebuttura",
        "tracking_id": "170742527"
    },
    {
        "urn_id": "ACoAACE7tIYBUOSDpApP9MfDHJ7UOJpnaMj7aCs",
        "distance": "DISTANCE_2",
        "public_id": "camila-moscosqui-rigueira-71a886136",
        "tracking_id": "557560966"
    },
    {
        "urn_id": "ACoAABftuJsBozBh4xwW1SD2w-hWuM-o8g1G1Hg",
        "distance": "DISTANCE_2",
        "public_id": "felipebellato",
        "tracking_id": "401455259"
    },
    {
        "urn_id": "ACoAAAo1kVYBrdgJYTtmSN4wq2WVdj5pBpErAMs",
        "distance": "DISTANCE_2",
        "public_id": "karolxavierleite",
        "tracking_id": "171282774"
    },
    {
        "urn_id": "ACoAABXiWv8BcJfsn5-gch4X9YKled-7Cd7K6dE",
        "distance": "DISTANCE_2",
        "public_id": "isabella-paciullo-gomes",
        "tracking_id": "367155967"
    },
    {
        "urn_id": "ACoAAAvJLyEBpAPol7ivQU_Sq1sCPv5LdmHek6w",
        "distance": "DISTANCE_2",
        "public_id": "ubirajarapelli",
        "tracking_id": "197734177"
    },
    {
        "urn_id": "ACoAABbw7IoBizmvExxKsniLBpBOFvovZvUqlmQ",
        "distance": "DISTANCE_2",
        "public_id": "mariana-pestana-faria",
        "tracking_id": "384887946"
    },
    {
        "urn_id": "ACoAABoqTIQB85PT4C6tsDuimSBwpYfaKAzw3d4",
        "distance": "DISTANCE_2",
        "public_id": "samanta-ciboto",
        "tracking_id": "438979716"
    },
    {
        "urn_id": "ACoAAAr7ZQ8Bkqp-d2UnUliLcGwP2aHb8gMmxpc",
        "distance": "DISTANCE_2",
        "public_id": "victor-mello-romero",
        "tracking_id": "184247567"
    },
    {
        "urn_id": "ACoAAAZO3TEBK-C-c57rfdF2pVurDuCZNCstvJ8",
        "distance": "DISTANCE_2",
        "public_id": "vanessafreires",
        "tracking_id": "105831729"
    },
    {
        "urn_id": "ACoAAAyhB1gBpy8izN7bvTmP7PTU5L87cS4kMpk",
        "distance": "DISTANCE_2",
        "public_id": "lacerdaeduardo",
        "tracking_id": "211879768"
    },
    {
        "urn_id": "ACoAACH4SfAB7yRLK3ivfIyKoaYHPMLabwcitMc",
        "distance": "DISTANCE_2",
        "public_id": "natália-isepi-980a4613a",
        "tracking_id": "569919984"
    },
    {
        "urn_id": "ACoAABxrJ48B9dYhz8crmuy5Q9KlvlJQsqr7Q5w",
        "distance": "DISTANCE_2",
        "public_id": "jadyjacques",
        "tracking_id": "476784527"
    },
    {
        "urn_id": "ACoAACClDa4B7t5rBlwAFgNo5WI-jdsJ9GeQW2s",
        "distance": "DISTANCE_2",
        "public_id": "gafelix10",
        "tracking_id": "547687854"
    },
    {
        "urn_id": "ACoAAB5JWHEBjUDmIzsakLsx48i8hmVk684-3-4",
        "distance": "DISTANCE_2",
        "public_id": "vitoria-batistoti",
        "tracking_id": "508123249"
    },
    {
        "urn_id": "ACoAABlwErcBr9hrs5YUqCPylfarqrxAfcb-lNo",
        "distance": "DISTANCE_2",
        "public_id": "diego-henrique-costa-parente-49bb14ba",
        "tracking_id": "426775223"
    },
    {
        "urn_id": "ACoAAAa6g54BTgpr4AkcBhcQawON4CQbLQ_y7Q0",
        "distance": "DISTANCE_2",
        "public_id": "guilhermeestrela",
        "tracking_id": "112886686"
    },
    {
        "urn_id": "ACoAACdqDBYBTQb8S6-966LY-iM4c7LBvdYX_Do",
        "distance": "DISTANCE_2",
        "public_id": "patriciapicardi",
        "tracking_id": "661261334"
    },
    {
        "urn_id": "ACoAAAYOn7gB87O3YY6ycebuUMG_q6SHenO7NXI",
        "distance": "DISTANCE_2",
        "public_id": "bruno-h-santos",
        "tracking_id": "101621688"
    },
    {
        "urn_id": "ACoAABfav8gB6v4tYOxE8cBzVHfZKjB25V_0444",
        "distance": "DISTANCE_2",
        "public_id": "marcelo-sassaki-148044b2",
        "tracking_id": "400211912"
    },
    {
        "urn_id": "ACoAACEkGZwBA22b_iFMrtkQ2jw7YGfaXH1ngn0",
        "distance": "DISTANCE_2",
        "public_id": "mirella-souza",
        "tracking_id": "556013980"
    },
    {
        "urn_id": "ACoAAAtfTaYBmF9WOVaTiFzQZ2HXZm1vF4Sbj8A",
        "distance": "DISTANCE_2",
        "public_id": "felipe-laprano",
        "tracking_id": "190795174"
    },
    {
        "urn_id": "ACoAABPmU28BoYIhqKcuvfP0NQXJvQWSxHL9Kec",
        "distance": "DISTANCE_2",
        "public_id": "matheus-souza-03b98793",
        "tracking_id": "333861743"
    },
    {
        "urn_id": "ACoAABXzvkkBiuPUzUrk-6kFk1UbU4_eHjLKXL8",
        "distance": "DISTANCE_2",
        "public_id": "douglas-real-b75411a3",
        "tracking_id": "368295497"
    },
    {
        "urn_id": "ACoAABry0S4Bl5tUilsdVIXCPgfAou_qDVODXzg",
        "distance": "DISTANCE_2",
        "public_id": "amon-lara-03a4b8107",
        "tracking_id": "452120878"
    },
    {
        "urn_id": "ACoAAATg7A4BCujERGKhdN3jmgrYoxSNfevMBTA",
        "distance": "DISTANCE_2",
        "public_id": "rodolfooviana",
        "tracking_id": "81849358"
    },
    {
        "urn_id": "ACoAABmRAsQBGbMpDlivizBV1K7W0HznB73lXc4",
        "distance": "DISTANCE_2",
        "public_id": "helton-andreazza-718795bb",
        "tracking_id": "428933828"
    },
    {
        "urn_id": "ACoAAB04cJIB5AiAEIPvsm3s-xHOl-Yux-DUt_Q",
        "distance": "DISTANCE_2",
        "public_id": "gerhard-p",
        "tracking_id": "490238098"
    },
    {
        "urn_id": "ACoAABdKVssBmLTrMBgMTt5DkaB9Gb3PLBnAcvA",
        "distance": "DISTANCE_2",
        "public_id": "dgosantos89",
        "tracking_id": "390747851"
    },
    {
        "urn_id": "ACoAAATNJUkBhr9bI9FxPHy98QxAHeTHDI375rI",
        "distance": "DISTANCE_2",
        "public_id": "leandroardisson",
        "tracking_id": "80553289"
    },
    {
        "urn_id": "ACoAABfwVdUBWg3XupyqgBBYjVy2y5o2e2azX5k",
        "distance": "DISTANCE_2",
        "public_id": "ericksontakano",
        "tracking_id": "401626581"
    },
    {
        "urn_id": "ACoAAActnEkB2ddP5VNMHNFhnsLzseN4esburcw",
        "distance": "DISTANCE_2",
        "public_id": "hrs-henrique",
        "tracking_id": "120429641"
    },
    {
        "urn_id": "ACoAAA9Ex2EBXM9MVJ96DYfmUEj4CeK7nx0_nWY",
        "distance": "DISTANCE_2",
        "public_id": "ingridy-martins",
        "tracking_id": "256165729"
    },
    {
        "urn_id": "ACoAABfPoMEBV4Faaz6Dd5p7SL75zjUZf4aOPaE",
        "distance": "DISTANCE_2",
        "public_id": "vinícius-moraes-401952b1",
        "tracking_id": "399483073"
    },
    {
        "urn_id": "ACoAAAgBUigBJ4Dw6GyO4E0b-AhBLBBJ_EaJLjI",
        "distance": "DISTANCE_2",
        "public_id": "bruno-menegotto",
        "tracking_id": "134304296"
    },
    {
        "urn_id": "ACoAABjc9vYBnLriRQd1zsWCT7oV36eOhdOytqE",
        "distance": "DISTANCE_3",
        "public_id": "luizpaulopontes",
        "tracking_id": "417134326"
    },
    {
        "urn_id": "ACoAAArL9I0BEaeGGHOdpS4XUWNP6mF436Us010",
        "distance": "DISTANCE_2",
        "public_id": "rafaelsanchesdev",
        "tracking_id": "181138573"
    },
    {
        "urn_id": "ACoAAAtWeAYBQZa6u4Xy5Op0P1SqgZLaf6wH6XI",
        "distance": "DISTANCE_2",
        "public_id": "humbertoferreirajr",
        "tracking_id": "190216198"
    },
    {
        "urn_id": "ACoAAAR9fucBisygU5KHxy9eHuHilo_ntghGyjQ",
        "distance": "DISTANCE_2",
        "public_id": "alexandre-vieira-83328b21",
        "tracking_id": "75333351"
    },
    {
        "urn_id": "ACoAABm6ikkBSSCYyQa9_4X6IOSH9kIWLITtFBI",
        "distance": "DISTANCE_2",
        "public_id": "guilhermeluisteixeira",
        "tracking_id": "431655497"
    },
    {
        "urn_id": "ACoAACmssEkBwBRPWqDoPMnYlErwa0n09FWapis",
        "distance": "DISTANCE_2",
        "public_id": "filippopaulino",
        "tracking_id": "699183177"
    },
    {
        "urn_id": "ACoAACAxjKMBEzJ9Gt4fxcYCltM_DjDI790B2Jk",
        "distance": "DISTANCE_2",
        "public_id": "gdealmeida1885",
        "tracking_id": "540118179"
    },
    {
        "urn_id": "ACoAAAOI1yEBP3by2UY4TgzPzQjLeELhiVm_9QA",
        "distance": "DISTANCE_2",
        "public_id": "thiago-pereira-aa9a3817",
        "tracking_id": "59299617"
    },
    {
        "urn_id": "ACoAAASR_0oBVUHrAZCp2vK5OIzcQMxbbcDSJxI",
        "distance": "DISTANCE_2",
        "public_id": "simone-gouvêa-",
        "tracking_id": "76676938"
    },
    {
        "urn_id": "ACoAAA-sjwUBU8aWjPsgkkCO3PmEeN6raxrvncQ",
        "distance": "DISTANCE_2",
        "public_id": "jonasfernandes",
        "tracking_id": "262967045"
    },
    {
        "urn_id": "ACoAABBzLtgBgw2Eel9sAngCOm0c-iT8hykXCEo",
        "distance": "DISTANCE_2",
        "public_id": "guilherme-milfont-02051578",
        "tracking_id": "275984088"
    },
    {
        "urn_id": "ACoAAAViI2gBcKxrdf_tnBlbwmTTvNLHYdCS7DE",
        "distance": "DISTANCE_2",
        "public_id": "maxnovais",
        "tracking_id": "90317672"
    },
    {
        "urn_id": "ACoAACZKzcgBCwoDt6nGX9cqV91HZ-v6MJK9f98",
        "distance": "DISTANCE_2",
        "public_id": "mayara-melissa-souza-4b419815b",
        "tracking_id": "642436552"
    },
    {
        "urn_id": "ACoAABKrjVcB8x1zaIaxa-EWHJyWIG3i-VdmYFA",
        "distance": "DISTANCE_2",
        "public_id": "lucas-sales",
        "tracking_id": "313232727"
    },
    {
        "urn_id": "ACoAAAus8j8BfCoABN6Xn7KPiZNIu9JI3KzgMnc",
        "distance": "DISTANCE_2",
        "public_id": "khwesten",
        "tracking_id": "195883583"
    },
    {
        "urn_id": "ACoAACCsKBsB7YO6Kw4ajO4frnCeO20qMl_orzg",
        "distance": "DISTANCE_2",
        "public_id": "lorranyabrantes",
        "tracking_id": "548153371"
    },
    {
        "urn_id": "ACoAABIkMWkB-gzOnm_-pUfi-ojDSLWTHlD7FtQ",
        "distance": "DISTANCE_2",
        "public_id": "fllsouto",
        "tracking_id": "304361833"
    },
    {
        "urn_id": "ACoAABaegtIBDdhMca3YAmjGzZgSfr-pT4U9pig",
        "distance": "DISTANCE_2",
        "public_id": "harllen-souza-5aa10aa7",
        "tracking_id": "379486930"
    },
    {
        "urn_id": "ACoAABR788sB0c4kaMU-S95J1t3T0dbw6yekEV4",
        "distance": "DISTANCE_2",
        "public_id": "hedenica",
        "tracking_id": "343667659"
    },
    {
        "urn_id": "ACoAACv7JYgBkWTO3qy8-FzVxn7rpTPeKtc4DxI",
        "distance": "DISTANCE_2",
        "public_id": "naiaradominguesgestao",
        "tracking_id": "737879432"
    },
    {
        "urn_id": "ACoAABXuoNIBBT4kG-jL-3BpeBBIaDKMI-jNih8",
        "distance": "DISTANCE_2",
        "public_id": "victortademos",
        "tracking_id": "367960274"
    },
    {
        "urn_id": "ACoAABWlqroBILFiL5Bqf7cs0YSm2kbAzxDFaVs",
        "distance": "DISTANCE_2",
        "public_id": "guilhermeluizdesouza",
        "tracking_id": "363178682"
    },
    {
        "urn_id": "ACoAACHAcswBqE5VRnmUILksBCZRg0xZQgKGgoY",
        "distance": "DISTANCE_2",
        "public_id": "elluy",
        "tracking_id": "566260428"
    },
    {
        "urn_id": "ACoAABL7o44BRYHEZH-iZsvolNjCYXOgW1GqhDU",
        "distance": "DISTANCE_3",
        "public_id": "mairarabelo",
        "tracking_id": "318481294"
    },
    {
        "urn_id": "ACoAACG87Z4BocaexptxIMl77RLoz4YC-BXTJo8",
        "distance": "DISTANCE_2",
        "public_id": "gabrielsaints",
        "tracking_id": "566029726"
    },
    {
        "urn_id": "ACoAAAcpyssB-3Z_qPYtf10LzRXMsYFX-J7g4n0",
        "distance": "DISTANCE_2",
        "public_id": "brunosilva-engenharia-produção-civil",
        "tracking_id": "120179403"
    },
    {
        "urn_id": "ACoAAAgCM-gB8YmzUpSa4C1y-E4KsX_IS7HApVo",
        "distance": "DISTANCE_3",
        "public_id": "lucasrcolucci",
        "tracking_id": "134362088"
    },
    {
        "urn_id": "ACoAAB8TkasB6Umzr9BwkkbcpB3-kDCor6-l7ek",
        "distance": "DISTANCE_3",
        "public_id": "guilhermercb",
        "tracking_id": "521376171"
    },
    {
        "urn_id": "ACoAABePDyoBmfPLsqpLYMPAL78UKGBYWjji9nQ",
        "distance": "DISTANCE_2",
        "public_id": "vitor-de-souza-vanderley-60a451b0",
        "tracking_id": "395251498"
    },
    {
        "urn_id": "ACoAACKf1w4BMgpz2NEaK1XXtxufLR2uWz7Go40",
        "distance": "DISTANCE_3",
        "public_id": "kelly-biazi-412661142",
        "tracking_id": "580900622"
    },
    {
        "urn_id": "ACoAAAz1jFsByWW5_98nHcIn3WdUG2OW2sjk96Y",
        "distance": "DISTANCE_3",
        "public_id": "anarafaelagomes",
        "tracking_id": "217418843"
    },
    {
        "urn_id": "ACoAAB4PMhgBEzoSNuqKH9QTKxvuD4hkzvWG318",
        "distance": "DISTANCE_2",
        "public_id": "deboraferreira",
        "tracking_id": "504312344"
    },
    {
        "urn_id": "ACoAAA8qXIYBMLjg3AhIBCY02pCD5MW9d8Au7uM",
        "distance": "DISTANCE_3",
        "public_id": "askanayama",
        "tracking_id": "254434438"
    },
    {
        "urn_id": "ACoAAArwthABgOQOfsWljSiH5Jc51sXi8J5oW2g",
        "distance": "DISTANCE_3",
        "public_id": "letícia-valim-69457751",
        "tracking_id": "183547408"
    },
    {
        "urn_id": "ACoAAAx9T-MBScpqzuC8-xq7d92dxQ71FXousdw",
        "distance": "DISTANCE_3",
        "public_id": "laizabuchala",
        "tracking_id": "209539043"
    },
    {
        "urn_id": "ACoAAAKTHfYBbpe8LEFesHCHgm8Mfu9E6PDjgzc",
        "distance": "DISTANCE_3",
        "public_id": "diogenesjusto",
        "tracking_id": "43195894"
    },
    {
        "urn_id": "ACoAAA3uRY8BbwA9REBSmkCA3yCAYIcYgQ5cm3U",
        "distance": "DISTANCE_3",
        "public_id": "rmathias",
        "tracking_id": "233719183"
    },
    {
        "urn_id": "ACoAAAJBb_QBexvpknKIWFZ9OXq2OsvG9OFSMVA",
        "distance": "DISTANCE_3",
        "public_id": "bruno-barmak",
        "tracking_id": "37842932"
    },
    {
        "urn_id": "ACoAAB56XjMB8IZyEwwdbuGOhNiTYxYOx4WgWTI",
        "distance": "DISTANCE_3",
        "public_id": "beatriznonato",
        "tracking_id": "511335987"
    },
    {
        "urn_id": "ACoAACMBIOoBV762Xb5Q5fhIdHQc_CuSj1X7kiU",
        "distance": "DISTANCE_3",
        "public_id": "marcus-xavier-122817144",
        "tracking_id": "587276522"
    },
    {
        "urn_id": "ACoAAAQnI6UBTIy9ZKELKBwaXwGxGwvu1JHUH0I",
        "distance": "DISTANCE_3",
        "public_id": "brunopcallegari",
        "tracking_id": "69673893"
    },
    {
        "urn_id": "ACoAAAIED8wBSPwwEUkmYTF68m-k3K3HuFni6H0",
        "distance": "DISTANCE_3",
        "public_id": "giseletakekawa",
        "tracking_id": "33820620"
    },
    {
        "urn_id": "ACoAAAQnJ-IB_anshmUGxRp_NRmr0msYW18ZTd4",
        "distance": "DISTANCE_3",
        "public_id": "rodrigovcam",
        "tracking_id": "69674978"
    },
    {
        "urn_id": "ACoAAAlfgaUBXo-d5V5c-1TLuXwQXffqkP-Kv3s",
        "distance": "DISTANCE_3",
        "public_id": "luizsamico",
        "tracking_id": "157254053"
    },
    {
        "urn_id": "ACoAABOOfO0Bn5BVLUawBs4oqpo-YYnTHETq4MM",
        "distance": "DISTANCE_3",
        "public_id": "ana-naressi",
        "tracking_id": "328105197"
    },
    {
        "urn_id": "ACoAABPWW44BSZbMlSAHLQ1s_-TG9U2Llud3x1A",
        "distance": "DISTANCE_3",
        "public_id": "rodrigo-makoto",
        "tracking_id": "332815246"
    },
    {
        "urn_id": "ACoAAA6PzoMBbuUDTPPGHT8KlsfXpOE6rh9f1Fo",
        "distance": "DISTANCE_3",
        "public_id": "mayarabrum",
        "tracking_id": "244305539"
    },
    {
        "urn_id": "ACoAAAYGGzEBybeklx0oWBoVnJE80Iy24f4Y1Tc",
        "distance": "DISTANCE_3",
        "public_id": "tiagoavelar",
        "tracking_id": "101063473"
    },
    {
        "urn_id": "ACoAABxCp0wB7cbo3B__48DF4z9FIvFWOcsNZco",
        "distance": "DISTANCE_3",
        "public_id": "luciana-carvalho-dos-santos-b24950112",
        "tracking_id": "474130252"
    },
    {
        "urn_id": "ACoAAAh1Op0BFb0XfWMI_y-pO1JqFaTt-N6t9ek",
        "distance": "DISTANCE_3",
        "public_id": "orafapires",
        "tracking_id": "141900445"
    },
    {
        "urn_id": "ACoAABGD94QBd1bs_PMx7m_JxdLERATQ5B2E_uQ",
        "distance": "DISTANCE_3",
        "public_id": "laura-a-della-nina",
        "tracking_id": "293861252"
    },
    {
        "urn_id": "ACoAABhryikBkeRNjl0GYNtqNRrCfr8s8aaTgxo",
        "distance": "DISTANCE_3",
        "public_id": "karen-giordano-ab5268b5",
        "tracking_id": "409717289"
    },
    {
        "urn_id": "ACoAAAbgp20BBP_g4m6EqCSkx8pjDKCDL8Bwdkg",
        "distance": "DISTANCE_3",
        "public_id": "juliamluz",
        "tracking_id": "115386221"
    },
    {
        "urn_id": "ACoAAB_Msj4BlqKhk5iQWIXzC5M97sMoqpEhbzo",
        "distance": "DISTANCE_3",
        "public_id": "rodrigo-botti",
        "tracking_id": "533508670"
    },
    {
        "urn_id": "ACoAABwa5wYBRc4vhvkVCewLBN7mtMW48-FozSk",
        "distance": "DISTANCE_3",
        "public_id": "luiza-curto-camarano-406ab5111",
        "tracking_id": "471525126"
    },
    {
        "urn_id": "ACoAABRXHWYBe8G3PHCOtyuWtGwYlfVd0zeAUz4",
        "distance": "DISTANCE_3",
        "public_id": "nathassya-accioly-lins-vidal-rodrigues-79a35096",
        "tracking_id": "341253478"
    },
    {
        "urn_id": "ACoAAB_ZaaEBtF-PtB3aND_ubqN27vRs97jo_90",
        "distance": "DISTANCE_3",
        "public_id": "marilianascimento1996",
        "tracking_id": "534342049"
    },
    {
        "urn_id": "ACoAAA4F0u0BVECqmCXKfclcloGWD_HN-iK-H98",
        "distance": "DISTANCE_3",
        "public_id": "pupin",
        "tracking_id": "235262701"
    },
    {
        "urn_id": "ACoAAAZvgv0BsDAKPu49sZb3b_f5lgN7aRlM4bg",
        "distance": "DISTANCE_3",
        "public_id": "rafael-espindola-antunes",
        "tracking_id": "107971325"
    },
    {
        "urn_id": "ACoAAAHWzuMBAxuM2FP2DvvXBhyyRwxlp1V3gXI",
        "distance": "DISTANCE_3",
        "public_id": "mario-casanova-a033bba",
        "tracking_id": "30854883"
    },
    {
        "urn_id": "ACoAAAlMM2IBp5YwenxeSlv1tejPvCFbrA-wxK0",
        "distance": "DISTANCE_3",
        "public_id": "rseixas",
        "tracking_id": "155988834"
    },
    {
        "urn_id": "ACoAABmrvnMBbP8fXVrVCbZXTEikVnHDGoepaCo",
        "distance": "DISTANCE_3",
        "public_id": "rita-lino",
        "tracking_id": "430685811"
    },
    {
        "urn_id": "ACoAAAb9dQoBI0klMO7uyd6x6xyKLd06qruKJ0I",
        "distance": "DISTANCE_3",
        "public_id": "denneves",
        "tracking_id": "117273866"
    },
    {
        "urn_id": "ACoAABXcL7cB45nJnSJ3e1uOgWZL5R90NK0-2WU",
        "distance": "DISTANCE_3",
        "public_id": "déborarennócampos",
        "tracking_id": "366751671"
    },
    {
        "urn_id": "ACoAAA5p2G8BqAwH7TtcfpONd5DOrNsrjNQTNuw",
        "distance": "DISTANCE_3",
        "public_id": "carolinne-iglesias-vabo-97bb9868",
        "tracking_id": "241817711"
    },
    {
        "urn_id": "ACoAABnHTUsBK_XEJIFWxDQxKI-Kcxo-QeTqgBw",
        "distance": "DISTANCE_3",
        "public_id": "thaynaramozart",
        "tracking_id": "432491851"
    },
    {
        "urn_id": "ACoAAC0yZS8BDtgJt0z62Ds_YB1mX2UKG2Xpf9s",
        "distance": "DISTANCE_3",
        "public_id": "williana-leite-b53b41191",
        "tracking_id": "758277423"
    },
    {
        "urn_id": "ACoAACLrgmMBJexvASHh4EAUdtGL8WMBT7zWWpI",
        "distance": "DISTANCE_3",
        "public_id": "vinicius-leal-203253144",
        "tracking_id": "585859683"
    },
    {
        "urn_id": "ACoAAB91WHQBSIZrVDDbgQAiS14XVVpFyhUY3t8",
        "distance": "DISTANCE_3",
        "public_id": "dennis-holland",
        "tracking_id": "527784052"
    },
    {
        "urn_id": "ACoAAAHLUgwBS6e1mGEEb6vB7ZZ7uBzH5wAyhMk",
        "distance": "DISTANCE_3",
        "public_id": "heloisashiota",
        "tracking_id": "30102028"
    },
    {
        "urn_id": "ACoAAAAJTbABDaM1yBuBqKt0b2meBGLIHysz4Gw",
        "distance": "DISTANCE_3",
        "public_id": "martadteixeira",
        "tracking_id": "609712"
    },
    {
        "urn_id": "ACoAAB7xGUwBIwWYv1ipMVZpkw05l-s-ywdrrIA",
        "distance": "DISTANCE_3",
        "public_id": "giovanna-polverini",
        "tracking_id": "519117132"
    },
    {
        "urn_id": "ACoAAAwxAu0B5BxWNjacimfboojXbmEqPhxF6KU",
        "distance": "DISTANCE_3",
        "public_id": "jessicaborsari",
        "tracking_id": "204538605"
    },
    {
        "urn_id": "ACoAABt_zloBNJUc8-8zwmD57jlik_0IUpsv2vE",
        "distance": "DISTANCE_3",
        "public_id": "nicolas-zein",
        "tracking_id": "461360730"
    },
    {
        "urn_id": "ACoAAAy2QLEB42cPAXfdm8xNPdGVXw7Wzu4fIFo",
        "distance": "DISTANCE_3",
        "public_id": "gabrielefernandes",
        "tracking_id": "213270705"
    },
    {
        "urn_id": "ACoAAAnvvKQBkmZ4wBKRZdIjiV939-qzx8pQSW8",
        "distance": "DISTANCE_3",
        "public_id": "gabriel-artico-6b09b547",
        "tracking_id": "166706340"
    },
    {
        "urn_id": "ACoAAASQaiQBa3P-OfTH1fk8-afROSBjlS0INRk",
        "distance": "DISTANCE_3",
        "public_id": "erica-castro",
        "tracking_id": "76573220"
    },
    {
        "urn_id": "ACoAAApWCecBGT-0hkQo6rYPyd_eFbGcGszysXQ",
        "distance": "DISTANCE_3",
        "public_id": "mariany-pacheco-5730a94a",
        "tracking_id": "173410791"
    },
    {
        "urn_id": "ACoAACoBeWEBpH5bQdd4sXP4EUXH9AxGLRBSgsU",
        "distance": "DISTANCE_3",
        "public_id": "marina-de-matos-ferreira-569023178",
        "tracking_id": "704739681"
    },
    {
        "urn_id": "ACoAADKScDUB-nfh6xnUNMXG3HSQW1TvgdJPNhw",
        "distance": "DISTANCE_3",
        "public_id": "ian-menezes-7b11911b8",
        "tracking_id": "848457781"
    },
    {
        "urn_id": "ACoAABP38PEB2-q5El-cGEtUKd24NOK6ZF7uBvM",
        "distance": "DISTANCE_3",
        "public_id": "mariana-marsal-12924394",
        "tracking_id": "335016177"
    },
    {
        "urn_id": "ACoAACLwHJABB3qgW3x66RUBtWgd_oAz4AOwrUQ",
        "distance": "DISTANCE_3",
        "public_id": "mariana-dehon",
        "tracking_id": "586161296"
    },
    {
        "urn_id": "ACoAABmZ8oUB0f8Y0heitEzyzeTTSGlxSVGLx50",
        "distance": "DISTANCE_3",
        "public_id": "luiza-b-s-portinari-beja-631a18bb",
        "tracking_id": "429519493"
    },
    {
        "urn_id": "ACoAACvVBuEB23TknCE2Yx_GaVDaVp0210MZFGg",
        "distance": "DISTANCE_3",
        "public_id": "gustavodemoraesfurtado",
        "tracking_id": "735381217"
    },
    {
        "urn_id": "ACoAAANVyVMBQJqWuMwzuMdbpbJ6P1hMMUXHNzs",
        "distance": "DISTANCE_3",
        "public_id": "olavo-castro",
        "tracking_id": "55953747"
    },
    {
        "urn_id": "ACoAAAKogSMBwJglIaxJA7VcHuotxm73P3klUh0",
        "distance": "DISTANCE_3",
        "public_id": "rodrigovmiranda",
        "tracking_id": "44597539"
    },
    {
        "urn_id": "ACoAAA9MrtwBVXuPzQP04cyj08EuOmdPZvngQ1U",
        "distance": "DISTANCE_3",
        "public_id": "mariaclaramontes",
        "tracking_id": "256683740"
    },
    {
        "urn_id": "ACoAAA9QPM0BhRT5iyBOgPOgkm-HaT3EqEcm3Zc",
        "distance": "DISTANCE_3",
        "public_id": "claudiosajr",
        "tracking_id": "256916685"
    },
    {
        "urn_id": "ACoAAAIeaFEBWlrVYHcXhUkLr0JjVK_6vwOjl7Y",
        "distance": "DISTANCE_3",
        "public_id": "nunesrodrigo",
        "tracking_id": "35547217"
    },
    {
        "urn_id": "ACoAAAqSAHUBdNTZQp_vWqeunj3I6OjWdifdv6c",
        "distance": "DISTANCE_3",
        "public_id": "martabaungratz",
        "tracking_id": "177340533"
    },
    {
        "urn_id": "ACoAAA5lSDQBHwTSzq4aCEhBwQUtha9ZzxYjbbk",
        "distance": "DISTANCE_3",
        "public_id": "larissa-porto-eleutério-898a7368",
        "tracking_id": "241518644"
    },
    {
        "urn_id": "ACoAAAeaiRoB2EL-0OEwuIey4QyBFLJlmlAyahk",
        "distance": "DISTANCE_3",
        "public_id": "maxrota",
        "tracking_id": "127568154"
    },
    {
        "urn_id": "ACoAAATqT08BQJoefFZcOXP6ljopYLUk7x8Oj4E",
        "distance": "DISTANCE_3",
        "public_id": "rafaelsoldan",
        "tracking_id": "82464591"
    },
    {
        "urn_id": "ACoAAAbdzLQBkZteML-W7l4utpK6z6yVt32H0QE",
        "distance": "DISTANCE_3",
        "public_id": "fpavao",
        "tracking_id": "115199156"
    },
    {
        "urn_id": "ACoAAB8AgZABzp7FV7fDoUsaltJX48YLsoA0n4c",
        "distance": "DISTANCE_3",
        "public_id": "arufernanda",
        "tracking_id": "520126864"
    },
    {
        "urn_id": "ACoAABevAt8B0EGG2IyZT1EHh5uwssWu3iSXCpw",
        "distance": "DISTANCE_3",
        "public_id": "joaopedrodonairealbino",
        "tracking_id": "397345503"
    },
    {
        "urn_id": "ACoAAAOFmWQBNw6bZjriWOkOmS1Os8TuU6GBFB0",
        "distance": "DISTANCE_3",
        "public_id": "brunojankowisk",
        "tracking_id": "59087204"
    },
    {
        "urn_id": "ACoAACLnf-wBrgoi0MM-Xq7vYLoELGf3WtE9hmQ",
        "distance": "DISTANCE_3",
        "public_id": "felipe-nicolau-bonke-124147144",
        "tracking_id": "585596908"
    },
    {
        "urn_id": "ACoAABEBTikBbDXKG2ro9B6yzozVPB6PZ11r3D4",
        "distance": "DISTANCE_3",
        "public_id": "lucasisern",
        "tracking_id": "285298217"
    },
    {
        "urn_id": "ACoAABflQaQBsh4mgaxACRwuxWtAUiNhOwXN6wM",
        "distance": "DISTANCE_3",
        "public_id": "priscilalourinho",
        "tracking_id": "400900516"
    },
    {
        "urn_id": "ACoAAA6F4hMB8KyxH27B8J38rvgkmtj-ylOPtlM",
        "distance": "DISTANCE_3",
        "public_id": "tom-hayden",
        "tracking_id": "243655187"
    },
    {
        "urn_id": "ACoAACPHJL0BcrzWfKgiskRqWXRHXnR32lVTSvU",
        "distance": "DISTANCE_3",
        "public_id": "paularemuszka",
        "tracking_id": "600253629"
    },
    {
        "urn_id": "ACoAAChKMr0B61mTyjnOXbQ3Fv6dKMY8XFfzfhQ",
        "distance": "DISTANCE_3",
        "public_id": "fabiobara",
        "tracking_id": "675951293"
    },
    {
        "urn_id": "ACoAABL4lhUBwsjZEnoeRMTMbWv72pScxCOlUMU",
        "distance": "DISTANCE_3",
        "public_id": "caio-vaz-6457128a",
        "tracking_id": "318281237"
    },
    {
        "urn_id": "ACoAAAWNOmoBeD_P7JPftcJafnBtUXu4bqaHYOY",
        "distance": "DISTANCE_3",
        "public_id": "marcos-berto",
        "tracking_id": "93141610"
    },
    {
        "urn_id": "ACoAAAgNPkMB75VKkulQ2JEberLfQuPAG-QVk3I",
        "distance": "DISTANCE_3",
        "public_id": "otaviosueitt",
        "tracking_id": "135085635"
    },
    {
        "urn_id": "ACoAAARTgloBxjds53qViUhxE_P0JtXaG0j0D-I",
        "distance": "DISTANCE_3",
        "public_id": "felipe-coelho-lima",
        "tracking_id": "72581722"
    },
    {
        "urn_id": "ACoAAA9RQJcBzYQZoFaC9xLchc1Irs3EM2rFkMo",
        "distance": "DISTANCE_3",
        "public_id": "luísa-sartori-cofcewicz-operations-lastmile-startup",
        "tracking_id": "256983191"
    },
    {
        "urn_id": "ACoAAAMcS7QBc55JInb9rb2xC-trU3JNPrLp8H0",
        "distance": "DISTANCE_3",
        "public_id": "fernandofragoso",
        "tracking_id": "52186036"
    },
    {
        "urn_id": "ACoAAArwmacBoGqcbcrsVyWYUOGS_7x5dnPD7R8",
        "distance": "DISTANCE_3",
        "public_id": "rafael-alves-adib-43357351",
        "tracking_id": "183540135"
    },
    {
        "urn_id": "ACoAABOhTqYBcHoK4r8NW8c-cfxg7Yipq_aVI9M",
        "distance": "DISTANCE_3",
        "public_id": "dario-dragone-51a36592",
        "tracking_id": "329338534"
    },
    {
        "urn_id": "ACoAACC2a8wBT6RA31o_aa_6LyDStAqmh16g_Ig",
        "distance": "DISTANCE_3",
        "public_id": "felipe-corona-810973133",
        "tracking_id": "548826060"
    },
    {
        "urn_id": "ACoAAA5VfF4BKWlTj10EckoBsssYHG4sqdmUW-8",
        "distance": "DISTANCE_3",
        "public_id": "marcella-jyo",
        "tracking_id": "240483422"
    },
    {
        "urn_id": "ACoAAAYb1EwBlf9Z-g65Rq4Rt_D4T8S1x_k37Ss",
        "distance": "DISTANCE_3",
        "public_id": "regina-gomes-8103a52a",
        "tracking_id": "102487116"
    },
    {
        "urn_id": "ACoAAA0uPikBozS_x3V1BaOrBD_9TLYkoqTr2Yc",
        "distance": "DISTANCE_3",
        "public_id": "franciellelima",
        "tracking_id": "221134377"
    },
    {
        "urn_id": "ACoAAAvDLK8B6RimU0CLRkj9kRSZNj81eCIVDlc",
        "distance": "DISTANCE_3",
        "public_id": "luana-fernandes-6bb10956",
        "tracking_id": "197340335"
    },
    {
        "urn_id": "ACoAABaMzH4BAvm2DLxyifggoaZZzkcZWuGYiUc",
        "distance": "DISTANCE_3",
        "public_id": "leilaevelyn",
        "tracking_id": "378326142"
    },
    {
        "urn_id": "ACoAABqDfWgByzBKJjrHpXTt3Hd02BTWUqWOWno",
        "distance": "DISTANCE_3",
        "public_id": "andreblasques",
        "tracking_id": "444824936"
    },
    {
        "urn_id": "ACoAAB-P32wBD-GotxqqDPdZ36r7oP5m9-USpS8",
        "distance": "DISTANCE_3",
        "public_id": "luisgfelix",
        "tracking_id": "529522540"
    },
    {
        "urn_id": "ACoAAApDHmoBnDrlbBidbE5imx5niQsCZAazjcU",
        "distance": "DISTANCE_3",
        "public_id": "alisson-bezerra",
        "tracking_id": "172170858"
    },
    {
        "urn_id": "ACoAABZLDH0B-nkSbRlX8mp6r9IxUBnzVaa2Gys",
        "distance": "DISTANCE_3",
        "public_id": "raphaela-matiasi-🏳️‍🌈-139311a5",
        "tracking_id": "374017149"
    },
    {
        "urn_id": "ACoAACgfF-QBl0oLYnkK0ye_YuYzpkjCAoCaT7Y",
        "distance": "DISTANCE_3",
        "public_id": "guilherme-neves-884518169",
        "tracking_id": "673126372"
    },
    {
        "urn_id": "ACoAABNvdIwBqMtQbKnoknOMSE4LspLzaqR6a6s",
        "distance": "DISTANCE_3",
        "public_id": "carolline-massari",
        "tracking_id": "326071436"
    },
    {
        "urn_id": "ACoAABpGPJ8Bu4PeUf4E2qHrgixPwvtOIgljlAk",
        "distance": "DISTANCE_3",
        "public_id": "ana-carolina-faria-santana-913762103",
        "tracking_id": "440810655"
    },
    {
        "urn_id": "ACoAAAyDcDUBedLCvzx83zSkxfP7PC1FEjzqG1k",
        "distance": "DISTANCE_3",
        "public_id": "rafael-gomes-francisco",
        "tracking_id": "209940533"
    },
    {
        "urn_id": "ACoAABTwF5ABsTmny_gg1IGuDIV3GrZzkatjnbs",
        "distance": "DISTANCE_3",
        "public_id": "fernanda-magalhaes92",
        "tracking_id": "351278992"
    },
    {
        "urn_id": "ACoAABxc-IEBhc8OiWupILf6WiqE6zEmqihUT60",
        "distance": "DISTANCE_3",
        "public_id": "gabrielamellovieiradecastro",
        "tracking_id": "475854977"
    },
    {
        "urn_id": "ACoAAAUVZnQB4cL2SUhicywbHZ8_hCKiV3x6fP8",
        "distance": "DISTANCE_3",
        "public_id": "larissa-diacov-98469024",
        "tracking_id": "85288564"
    },
    {
        "urn_id": "ACoAABA4v7sBirUHMjk8YUBQK1_GmJVo0GYnLgI",
        "distance": "DISTANCE_3",
        "public_id": "iara-mattos-a2318877",
        "tracking_id": "272154555"
    },
    {
        "urn_id": "ACoAAAdbTzUBK0dqhUSQ_b1a1qQZbPvlzqTTH_A",
        "distance": "DISTANCE_3",
        "public_id": "eriknakata",
        "tracking_id": "123424565"
    },
    {
        "urn_id": "ACoAABlE-kMBfLHaba4vZSHUW1DKfuegDsUDWnk",
        "distance": "DISTANCE_3",
        "public_id": "ana-beatriz-silva-campos-b6bb91b9",
        "tracking_id": "423950915"
    },
    {
        "urn_id": "ACoAAAUAzBIBGE1XAHw-Ncn2pMKNWmbdJsYhYO8",
        "distance": "DISTANCE_3",
        "public_id": "tayse-lima-boletini-🏳️‍🌈-50213b24",
        "tracking_id": "83938322"
    },
    {
        "urn_id": "ACoAADFu8Y0B-rA4aYxUCPMV2kMEM4OPIl3rm2g",
        "distance": "DISTANCE_3",
        "public_id": "jhonatan-militão-🏳️‍🌈-5518ba1b1",
        "tracking_id": "829354381"
    },
    {
        "urn_id": "ACoAAATfPWsBD4FRUvCseFn88MecXRa-hn6i66k",
        "distance": "DISTANCE_3",
        "public_id": "thales-hara-88b45a23",
        "tracking_id": "81739115"
    },
    {
        "urn_id": "ACoAACflH7IBMEcwi0Q-x2Y3mi3XYsOzAqsnrAA",
        "distance": "DISTANCE_3",
        "public_id": "lidianecesario",
        "tracking_id": "669327282"
    },
    {
        "urn_id": "ACoAAB7WiFgBGvQ8a9O9zApPdkM3-G4jsgm1pSg",
        "distance": "DISTANCE_3",
        "public_id": "william-gimenes",
        "tracking_id": "517376088"
    },
    {
        "urn_id": "ACoAAByDVUoB64u3wNXgpo7TVmgSy4a1h-Z5heA",
        "distance": "DISTANCE_3",
        "public_id": "ana-senna-b76255114",
        "tracking_id": "478369098"
    },
    {
        "urn_id": "ACoAABuRswkBzGpvOZ0-NTNsRYHfcbu4crJfN6c",
        "distance": "DISTANCE_3",
        "public_id": "ciceropslima",
        "tracking_id": "462533385"
    },
    {
        "urn_id": "ACoAACPhPawB9iNW4hzYOZ0jOhPUV112Ih-aaxY",
        "distance": "DISTANCE_3",
        "public_id": "amanda-wendt",
        "tracking_id": "601963948"
    },
    {
        "urn_id": "ACoAAAdvhAMBQ2prCFUqHseciZOTRFIVAsjAHi8",
        "distance": "DISTANCE_3",
        "public_id": "cesar-arantes",
        "tracking_id": "124748803"
    },
    {
        "urn_id": "ACoAAC-CLssBUtRZkteGHZZIMNDoJnHvM_VVPME",
        "distance": "DISTANCE_3",
        "public_id": "cris-leite-da-costa-063b261a2",
        "tracking_id": "797060811"
    },
    {
        "urn_id": "ACoAABsnA-EBQjjl5GNsxPdX-xR1GUs6mIzvOWg",
        "distance": "DISTANCE_3",
        "public_id": "jooshuarichter",
        "tracking_id": "455541729"
    },
    {
        "urn_id": "ACoAABTG3uUBN366eLEZkrBUu1Y8JWx9qs-EfbE",
        "distance": "DISTANCE_3",
        "public_id": "luiz-fontenelle",
        "tracking_id": "348577509"
    },
    {
        "urn_id": "ACoAABXsPm4B6wrpiGsdV-zntxdmCuT5N5kC34M",
        "distance": "DISTANCE_3",
        "public_id": "julianaabud",
        "tracking_id": "367804014"
    },
    {
        "urn_id": "ACoAAA9fE34BUJOPGLIg7uo850Dum6bSVXO9SDk",
        "distance": "DISTANCE_3",
        "public_id": "camila-nascimento-4a644972",
        "tracking_id": "257889150"
    },
    {
        "urn_id": "ACoAAAX9xs0BbMA-QuEroxuFOn5d_tvXCYuNlU0",
        "distance": "DISTANCE_3",
        "public_id": "raul-steven-soto-sabrera-a917b529",
        "tracking_id": "100517581"
    },
    {
        "urn_id": "ACoAAA0AkyABfPldyB9DAadmHn876lpBVjf83F8",
        "distance": "DISTANCE_3",
        "public_id": "thiago-boufelli",
        "tracking_id": "218141472"
    },
    {
        "urn_id": "ACoAAAWx3EYB0wKqjB9WcfIyRpmE3AQVJn45peU",
        "distance": "DISTANCE_3",
        "public_id": "lauradmeirelles",
        "tracking_id": "95542342"
    },
    {
        "urn_id": "ACoAABp5vZEB1-dL89r2Tjpp4eWsf_0rjiE-Y6w",
        "distance": "DISTANCE_3",
        "public_id": "gustavotdias",
        "tracking_id": "444186001"
    },
    {
        "urn_id": "ACoAAAH99zQBClNM9mC1NXg_IoCRTZOhiJPt9xQ",
        "distance": "DISTANCE_3",
        "public_id": "thaisw",
        "tracking_id": "33421108"
    },
    {
        "urn_id": "ACoAAASRPusBJ53J7EWj4lHafvxJqpq7ki-fhGk",
        "distance": "DISTANCE_3",
        "public_id": "josesalibajr",
        "tracking_id": "76627691"
    },
    {
        "urn_id": "ACoAAA-Ad8AB4ZvioDBRU8Prnt8p6e_BNGCSbX0",
        "distance": "DISTANCE_3",
        "public_id": "maria-julia-pereira-kondic-99412373",
        "tracking_id": "260077504"
    },
    {
        "urn_id": "ACoAAAzHyvEB2X5HUZG9HWTHV4i_WVbW1Lo4_mk",
        "distance": "DISTANCE_2",
        "public_id": "alansc",
        "tracking_id": "214420209"
    },
    {
        "urn_id": "ACoAAAhTaPsBmBxnESt4vXeG1poZUwzC-DXipRY",
        "distance": "DISTANCE_2",
        "public_id": "tinabcruz",
        "tracking_id": "139684091"
    },
    {
        "urn_id": "ACoAABk0qEkBSJLwZ9dbXIS6n6-DC1cK2kYmFKU",
        "distance": "DISTANCE_2",
        "public_id": "maurafogaca",
        "tracking_id": "422881353"
    },
    {
        "urn_id": "ACoAABhSnfEBf_Yt5zzdKnixznCavrav_-tE2uU",
        "distance": "DISTANCE_2",
        "public_id": "joão-vitor-moreira-chieregatti",
        "tracking_id": "408067569"
    },
    {
        "urn_id": "ACoAAA9hUm8B7vRBwm_sfICPL3L3WXYKau_L28Y",
        "distance": "DISTANCE_2",
        "public_id": "thamyres-moraes",
        "tracking_id": "258036335"
    },
    {
        "urn_id": "ACoAAAWjbskBxD7yIDFTBSCc7NSVvWbgZa5ZVS4",
        "distance": "DISTANCE_2",
        "public_id": "camilocosta",
        "tracking_id": "94596809"
    },
    {
        "urn_id": "ACoAACBE-d8Bw0P9jxshB0RofGg09rxe83NrzqQ",
        "distance": "DISTANCE_2",
        "public_id": "matheus-viriato",
        "tracking_id": "541391327"
    },
    {
        "urn_id": "ACoAAAlZcVoB1QjESMLVlnYKFxaUJIQPTlKbiAU",
        "distance": "DISTANCE_2",
        "public_id": "frontfabi",
        "tracking_id": "156856666"
    },
    {
        "urn_id": "ACoAAB6wb0sBBTxKE43sqpKW1qJ3X2wFpxojmTY",
        "distance": "DISTANCE_3",
        "public_id": "alice-felix-68b522124",
        "tracking_id": "514879307"
    },
    {
        "urn_id": "ACoAAC4b2mUBPtH161thn_SH485GAfYNyMm7Rqw",
        "distance": "DISTANCE_3",
        "public_id": "carolina-bruce-0850a0197",
        "tracking_id": "773577317"
    },
    {
        "urn_id": "ACoAAAi5IHkB_dIQAuUCR_l7fHHQX-9BC6NAZvo",
        "distance": "DISTANCE_3",
        "public_id": "gwolgien",
        "tracking_id": "146350201"
    },
    {
        "urn_id": "ACoAABrmWlABVIcgEcxAwoDW89j8z8FMcwDe9gc",
        "distance": "DISTANCE_3",
        "public_id": "dias-gabriel",
        "tracking_id": "451304016"
    },
    {
        "urn_id": "ACoAAA1hKhIBMeioKI88bTc44gksJsT4QHbD9Ck",
        "distance": "DISTANCE_3",
        "public_id": "sérgio-miragaia-lopes-jr-64221263",
        "tracking_id": "224471570"
    },
    {
        "urn_id": "ACoAAAPX96IBs-d3CTdo5JcGEZrOV8orY-uCAUE",
        "distance": "DISTANCE_3",
        "public_id": "ericorreia",
        "tracking_id": "64485282"
    },
    {
        "urn_id": "ACoAAAV1gcIB_6SFF55NZNPQ0qu1Hpv6ekI1Pk8",
        "distance": "DISTANCE_2",
        "public_id": "daviaragao",
        "tracking_id": "91587010"
    },
    {
        "urn_id": "ACoAAA4p928BltbGrSb6-oHFYB_u_8dAQVqJNT4",
        "distance": "DISTANCE_3",
        "public_id": "karen-ayub-17b6ba67",
        "tracking_id": "237631343"
    },
    {
        "urn_id": "ACoAAAVDetsB-8UC2at7KGKEQylA4CAcSeIs2t0",
        "distance": "DISTANCE_3",
        "public_id": "regis-brilhante",
        "tracking_id": "88308443"
    },
    {
        "urn_id": "ACoAABkxfI8BfP7ifEu1J8NgMCIMvnqYGZ6pOTE",
        "distance": "DISTANCE_3",
        "public_id": "nysandrotorres",
        "tracking_id": "422673551"
    },
    {
        "urn_id": "ACoAACRlS_wBNB4C8-uYLw1fcI-v7CRlX9cX2JY",
        "distance": "DISTANCE_3",
        "public_id": "denis-ikeda",
        "tracking_id": "610618364"
    },
    {
        "urn_id": "ACoAACJabsIBg0enJGTcZXNyrMN2HZdIFDshFGw",
        "distance": "DISTANCE_3",
        "public_id": "mariane-brandão-felix-002029141",
        "tracking_id": "576351938"
    },
    {
        "urn_id": "ACoAAAvMKbwBDz3TexEfUT4b-b5_TqjCoUF1rzw",
        "distance": "DISTANCE_3",
        "public_id": "danielateixo",
        "tracking_id": "197929404"
    },
    {
        "urn_id": "ACoAABW--CYBSbM1IsSunPPYszSvgts-LlMQqgQ",
        "distance": "DISTANCE_3",
        "public_id": "guilhermelb",
        "tracking_id": "364836902"
    },
    {
        "urn_id": "ACoAACaMyZ8B-LvMxR_Tbie1pemmFcmsn8EXEGE",
        "distance": "DISTANCE_3",
        "public_id": "beatrizsousamendes",
        "tracking_id": "646760863"
    },
    {
        "urn_id": "ACoAAA5m344Bc_2Wcg2U3eDHvLnXDEvSO394PfQ",
        "distance": "DISTANCE_3",
        "public_id": "leandro-machado-0bab0468",
        "tracking_id": "241622926"
    },
    {
        "urn_id": "ACoAAA2wk7QBeURvvmUZgwOM66ktmcrbZ1-qLeA",
        "distance": "DISTANCE_3",
        "public_id": "gustavohriques",
        "tracking_id": "229675956"
    },
    {
        "urn_id": "ACoAABs7DlgBmt4rml59cQWMo1Y7X1PiGWisav0",
        "distance": "DISTANCE_3",
        "public_id": "agathajuliani",
        "tracking_id": "456855128"
    },
    {
        "urn_id": "ACoAACQYuHABaO-4HujwovYC8PLvQJKeNn9Z77Y",
        "distance": "DISTANCE_3",
        "public_id": "larissayasunaka",
        "tracking_id": "605599856"
    },
    {
        "urn_id": "ACoAAAqqoLcBaYSNDxoNnj6hL0WGZTRD9gq3K9s",
        "distance": "DISTANCE_3",
        "public_id": "taynarasantos16",
        "tracking_id": "178954423"
    },
    {
        "urn_id": "ACoAAAe1IwkBEAK_5I5sjv8g-AHM3HuxYxertyw",
        "distance": "DISTANCE_3",
        "public_id": "raiza-b-s-santana",
        "tracking_id": "129311497"
    },
    {
        "urn_id": "ACoAAAXf-VcBWcSZ5D0y8Le73v6CybWgvWDT9P4",
        "distance": "DISTANCE_3",
        "public_id": "carlos-machado-73301329",
        "tracking_id": "98564439"
    },
    {
        "urn_id": "ACoAACXWYn8Bxb5vdIC6yGnljASU9Tfi3Y9b44Q",
        "distance": "DISTANCE_3",
        "public_id": "vinicius-vasques-genosa-13b719158",
        "tracking_id": "634806911"
    },
    {
        "urn_id": "ACoAAAVIWcwBkj7w1MEiQo6o_mvhlIsnzYnqBQ0",
        "distance": "DISTANCE_3",
        "public_id": "marcio-gustavo-chahad-1a482125",
        "tracking_id": "88627660"
    },
    {
        "urn_id": "ACoAABvT6bEBeHHnRBQ4VLKyQTn6kq9lN2MMfBI",
        "distance": "DISTANCE_3",
        "public_id": "ana-carolina-bruno-machado-ba9430110",
        "tracking_id": "466872753"
    },
    {
        "urn_id": "ACoAACbo3OUBjsq42zx3501eQXGYi5m7XURRLjU",
        "distance": "DISTANCE_3",
        "public_id": "lorena-rabelo",
        "tracking_id": "652795109"
    },
    {
        "urn_id": "ACoAAAi1NwIBwbTRcUr9Lq2atSPyOIETix4vRGc",
        "distance": "DISTANCE_3",
        "public_id": "thais-m-freitas",
        "tracking_id": "146093826"
    },
    {
        "urn_id": "ACoAABe2lQIBLAZts8CQVb0Ub-OZ3K7zLl8XXb0",
        "distance": "DISTANCE_3",
        "public_id": "guilherme-ribeiro-5422a0b1",
        "tracking_id": "397841666"
    },
    {
        "urn_id": "ACoAACRzc2gBlOAWoC1FJ6wKHi0ogQXhpWdD1QI",
        "distance": "DISTANCE_3",
        "public_id": "gabriel-colchiesqui",
        "tracking_id": "611545960"
    },
    {
        "urn_id": "ACoAAB5VLlgBPfd_4MRDJD2ufxxTuwWY-2EkgL4",
        "distance": "DISTANCE_3",
        "public_id": "gustavo-almansa-rodrigues",
        "tracking_id": "508898904"
    },
    {
        "urn_id": "ACoAACQHu5cBhLnWfgUWV32by8ge7XUjdIorRIM",
        "distance": "DISTANCE_3",
        "public_id": "graziella-rocha-73353614a",
        "tracking_id": "604486551"
    },
    {
        "urn_id": "ACoAACfW1wsBP5ml64Dz7yXUcHGOpVsBZ2_VVXE",
        "distance": "DISTANCE_3",
        "public_id": "camilla-bueno",
        "tracking_id": "668391179"
    },
    {
        "urn_id": "ACoAACCBF14Bne_ygFkOgAOFnRHmHNEWiEG5Hl0",
        "distance": "DISTANCE_3",
        "public_id": "giovana-tavares",
        "tracking_id": "545331038"
    },
    {
        "urn_id": "ACoAACEZ9NkBo3Wm6vxhY4tDdfThddJNrVZNGB8",
        "distance": "DISTANCE_3",
        "public_id": "hellendecastro",
        "tracking_id": "555349209"
    },
    {
        "urn_id": "ACoAABebHTgBeb1tyCPYdksVSCbVbBtDaoogzAk",
        "distance": "DISTANCE_3",
        "public_id": "juliana-jalloule",
        "tracking_id": "396041528"
    },
    {
        "urn_id": "ACoAAAaG7GsBc12jy97Z9QUNVNxi10dv71Hzi7Y",
        "distance": "DISTANCE_3",
        "public_id": "erik-menini-arimathéa-3a380b30",
        "tracking_id": "109505643"
    },
    {
        "urn_id": "ACoAAAWLleQBknnKmiRpfeec_Lzl_XtR6BUaI5g",
        "distance": "DISTANCE_3",
        "public_id": "henrique-freitas-1181a727",
        "tracking_id": "93033956"
    },
    {
        "urn_id": "ACoAAAk-u9UBPm3bo3UqGEeOnuM1GpaBdvWHeX0",
        "distance": "DISTANCE_3",
        "public_id": "renata-fernandes-699b4043",
        "tracking_id": "155106261"
    },
    {
        "urn_id": "ACoAABRifP8BBr3xwkAa6rxJ4FQWDGVJmtBA49I",
        "distance": "DISTANCE_3",
        "public_id": "luan-h-de-andrade-bbb64b96",
        "tracking_id": "341998847"
    },
    {
        "urn_id": "ACoAACzNvRwBVUHolzRthj0SnI8XnswST3RsYuw",
        "distance": "DISTANCE_3",
        "public_id": "lorenzo-lang",
        "tracking_id": "751680796"
    },
    {
        "urn_id": "ACoAAAX2CNUBVvnHmELvvjITMnHK5Wtn6jWIKPQ",
        "distance": "DISTANCE_3",
        "public_id": "isadora-monteiro-de-freitas",
        "tracking_id": "100010197"
    },
    {
        "urn_id": "ACoAACde06cBMR0IsIyO78IH37QRXDzCAlWleuo",
        "distance": "DISTANCE_3",
        "public_id": "yasminvsouza",
        "tracking_id": "660525991"
    },
    {
        "urn_id": "ACoAABH5fUcBWXzLmYkWBdnBYH2wv_rU7_lOLnM",
        "distance": "DISTANCE_3",
        "public_id": "rafael-bessa-8b3bab84",
        "tracking_id": "301563207"
    },
    {
        "urn_id": "ACoAACuhwbMBeS2EcP3Ytc5AWc3VwICeVhlmMjY",
        "distance": "DISTANCE_3",
        "public_id": "jessica-felizardo-gregorio-44319b185",
        "tracking_id": "732021171"
    },
    {
        "urn_id": "ACoAAByInQ4BpUVgIHFZzuDTrWqhY3PSk-rdC4I",
        "distance": "DISTANCE_3",
        "public_id": "danilopaggi",
        "tracking_id": "478715150"
    },
    {
        "urn_id": "ACoAABw_hxwBQOf1PZAIu_5qDWb6lU8zC7CSqys",
        "distance": "DISTANCE_3",
        "public_id": "romulosrosa",
        "tracking_id": "473925404"
    },
    {
        "urn_id": "ACoAAAq9giABpSuXUxy4rO1KL18qzVyZ81fTjsI",
        "distance": "DISTANCE_3",
        "public_id": "rafaellaesteves",
        "tracking_id": "180191776"
    },
    {
        "urn_id": "ACoAAClsZEQB_-EVQPX4S6hvHpYr0B_o18OyKK0",
        "distance": "DISTANCE_3",
        "public_id": "marianarodriguespimenta",
        "tracking_id": "694969412"
    },
    {
        "urn_id": "ACoAABprFkIBND0GAO83EN77UVkXCetNHIbmShA",
        "distance": "DISTANCE_3",
        "public_id": "luis-augusto-yokota-rizzo",
        "tracking_id": "443225666"
    },
    {
        "urn_id": "ACoAABrAW_EBIELvFuoBk6NdeIhtJUlq4TNnMAg",
        "distance": "DISTANCE_3",
        "public_id": "anita-haerdy",
        "tracking_id": "448814065"
    },
    {
        "urn_id": "ACoAABsQPfkBfy0qNlRlM0sWKq0nHzipZkxqqKw",
        "distance": "DISTANCE_3",
        "public_id": "marceloarrais",
        "tracking_id": "454049273"
    },
    {
        "urn_id": "ACoAACqDHRIBm2cukmM_-LXpUovHgx9mzd5iReU",
        "distance": "DISTANCE_3",
        "public_id": "césar-lúcio-da-silva-1aaa4017a",
        "tracking_id": "713235730"
    },
    {
        "urn_id": "ACoAAAVucLcBEJFpvAtxwMfpBRpHvT0zN04gdWA",
        "distance": "DISTANCE_3",
        "public_id": "jamesodasilva",
        "tracking_id": "91123895"
    },
    {
        "urn_id": "ACoAAAWnj_4BVw7luJ00plMwrtpZCOJZXXJ79IM",
        "distance": "DISTANCE_3",
        "public_id": "jonas-manabu-okawara",
        "tracking_id": "94867454"
    },
    {
        "urn_id": "ACoAAA6Iv2EByJKs7UCfdYMVKjiBHV3zPUzeIbA",
        "distance": "DISTANCE_3",
        "public_id": "brunosaantos",
        "tracking_id": "243842913"
    },
    {
        "urn_id": "ACoAACKO6C0BHc69ZXZKWJgoP_JiW2jwcbM3Uvk",
        "distance": "DISTANCE_3",
        "public_id": "guilherme-chuqui-179207142",
        "tracking_id": "579790893"
    },
    {
        "urn_id": "ACoAACK9YXYB868-ownbDv8hwL8Nf6BacENFLs4",
        "distance": "DISTANCE_3",
        "public_id": "anderson-teixeira-cx",
        "tracking_id": "582836598"
    },
    {
        "urn_id": "ACoAACmab0oBkWHok9ff3l5h1uYd2EOMdoCUm3k",
        "distance": "DISTANCE_3",
        "public_id": "lobobruna",
        "tracking_id": "697986890"
    },
    {
        "urn_id": "ACoAABijSv0Bmk76tf9VbS3UUHV5qtBrcxdPfvM",
        "distance": "DISTANCE_3",
        "public_id": "anderson-sousa",
        "tracking_id": "413354749"
    },
    {
        "urn_id": "ACoAABFPJ88BZeKIpQ6lkgF0E7yD2tBN3qLRvkc",
        "distance": "DISTANCE_3",
        "public_id": "wesmarcal",
        "tracking_id": "290400207"
    },
    {
        "urn_id": "ACoAACrMBdUBA61xN0x_ibmaPc10CHu2lMT3IhM",
        "distance": "DISTANCE_3",
        "public_id": "juliana-palacio",
        "tracking_id": "718013909"
    },
    {
        "urn_id": "ACoAAAWrrskBuxZ2aoHwYKSaTPXE8zXh2gwsHsQ",
        "distance": "DISTANCE_3",
        "public_id": "victoralho",
        "tracking_id": "95137481"
    },
    {
        "urn_id": "ACoAABLdMikBiF8X-5v23t3RLrIp5uCuXpmPvEI",
        "distance": "DISTANCE_3",
        "public_id": "rubens-sôto",
        "tracking_id": "316486185"
    },
    {
        "urn_id": "ACoAABXRLkQBvq1WkwWS-Z-y9df4cKno1Zknmkc",
        "distance": "DISTANCE_3",
        "public_id": "lucas-r-ferrari",
        "tracking_id": "366030404"
    },
    {
        "urn_id": "ACoAABGlMnABnmqSRRCJzJtPaNqJnAP23WZ2vxQ",
        "distance": "DISTANCE_3",
        "public_id": "isadorawright",
        "tracking_id": "296039024"
    },
    {
        "urn_id": "ACoAAAtFWCcBXcShlI8jEBaGMdqVk42wUTMh90A",
        "distance": "DISTANCE_3",
        "public_id": "felipe-cubas-4333b153",
        "tracking_id": "189093927"
    },
    {
        "urn_id": "ACoAABrQRFIBm56X36f_ySTBTuJqxKI1SYuptBM",
        "distance": "DISTANCE_3",
        "public_id": "andre-zagatti",
        "tracking_id": "449856594"
    },
    {
        "urn_id": "ACoAACcrGIQBMCo2DLWIn1k9hc2K9uT-xg4LwNA",
        "distance": "DISTANCE_3",
        "public_id": "matheus-silva-a840a6164",
        "tracking_id": "657135748"
    },
    {
        "urn_id": "ACoAAA-i9OMB_WmwPZ4c00QSWlWib8Jv3R8CXzM",
        "distance": "DISTANCE_3",
        "public_id": "giovannaluchetta",
        "tracking_id": "262337763"
    },
    {
        "urn_id": "ACoAAC4wZq4BKuImWO0HpUb5XiOhtFdJdNf7OKY",
        "distance": "DISTANCE_3",
        "public_id": "andré-silva-43a62b197",
        "tracking_id": "774923950"
    },
    {
        "urn_id": "ACoAACZghx8BRs6GnRGWLm8CvjAWsBSYGrV1oQg",
        "distance": "DISTANCE_3",
        "public_id": "gustavo-braga-39376415b",
        "tracking_id": "643860255"
    },
    {
        "urn_id": "ACoAABUrrO8B3uEOQj7VyJJSDJNM-4OCN0ooZAs",
        "distance": "DISTANCE_3",
        "public_id": "winnyehashimoto",
        "tracking_id": "355183855"
    },
    {
        "urn_id": "ACoAABVcAjABe3LZ9QDecQ_oETO8OV7OjYrTfHY",
        "distance": "DISTANCE_3",
        "public_id": "diogodi",
        "tracking_id": "358351408"
    },
    {
        "urn_id": "ACoAAASWmxwBG_McmSAJ1HQebgYRP1jBtlpoqSw",
        "distance": "DISTANCE_3",
        "public_id": "santananatalia",
        "tracking_id": "76978972"
    },
    {
        "urn_id": "ACoAAATrqLoBlVvZRGpAm3l7HQzSsBF6BuDsa6I",
        "distance": "DISTANCE_3",
        "public_id": "ajackoliveira",
        "tracking_id": "82553018"
    },
    {
        "urn_id": "ACoAACfGYZUBtp-w0D2J-QmbjyMJVDGU3ZnNXSg",
        "distance": "DISTANCE_3",
        "public_id": "debora-oliveira-299594167",
        "tracking_id": "667312533"
    },
    {
        "urn_id": "ACoAAAahZWgBMwhCL3qta_uhxyETdnu79E4QmVk",
        "distance": "DISTANCE_3",
        "public_id": "carlosalsj",
        "tracking_id": "111240552"
    },
    {
        "urn_id": "ACoAACWI5q8B-OfRFmRLRH1cASqRJhNJ7V1CM7M",
        "distance": "DISTANCE_3",
        "public_id": "ian-afrange-szterenzys-57ba8a156",
        "tracking_id": "629728943"
    },
    {
        "urn_id": "ACoAAARuRwABCoMpetewgh7ahY4LMLy2JZAcUtU",
        "distance": "DISTANCE_3",
        "public_id": "diegodcarrion",
        "tracking_id": "74336000"
    },
    {
        "urn_id": "ACoAACATf6YB_UE8NokvIkSsmfFU3xKfQ3st47g",
        "distance": "DISTANCE_3",
        "public_id": "viniciusabatte",
        "tracking_id": "538148774"
    },
    {
        "urn_id": "ACoAACsN8g4BUtfen2AVf6iS955wsVoE50xyPis",
        "distance": "DISTANCE_3",
        "public_id": "lucasmarques96",
        "tracking_id": "722334222"
    },
    {
        "urn_id": "ACoAACUL8P0Ba_S6pmPek-hzdBjunTNC4vMYIaI",
        "distance": "DISTANCE_3",
        "public_id": "marcela-chagas",
        "tracking_id": "621539581"
    },
    {
        "urn_id": "ACoAACW7ZvYBwCiGrbntNhMg5dH1nwtTHcJsDrQ",
        "distance": "DISTANCE_3",
        "public_id": "brunna-souza-dias-932005158",
        "tracking_id": "633038582"
    },
    {
        "urn_id": "ACoAAATQ1BoB3wuWsPD8wKhESMrjumykgLuKhtM",
        "distance": "DISTANCE_3",
        "public_id": "tati-tatsch",
        "tracking_id": "80794650"
    },
    {
        "urn_id": "ACoAABd8yIQBYq5SQpvpFeD1CIsgER_7izB7U_o",
        "distance": "DISTANCE_3",
        "public_id": "caique-bugorel-458b74ab",
        "tracking_id": "394053764"
    },
    {
        "urn_id": "ACoAABmtztYBxLxyL3FDXegCqu7gB0eYxgCmayo",
        "distance": "DISTANCE_3",
        "public_id": "camillecosta",
        "tracking_id": "430821078"
    },
    {
        "urn_id": "ACoAACH-RIQBu0tc3vl-pJpn1bNiTo5aTWM6a0A",
        "distance": "DISTANCE_3",
        "public_id": "daniel-nobre-684bb513a",
        "tracking_id": "570311812"
    },
    {
        "urn_id": "ACoAAALKA3MB0P8MWJBFlu991jOELaLu_O9nImg",
        "distance": "DISTANCE_3",
        "public_id": "camilazsantana",
        "tracking_id": "46793587"
    },
    {
        "urn_id": "ACoAACJxsoUBrAGKYd6nxR3ZN8Q5hkFdBmP4e9M",
        "distance": "DISTANCE_3",
        "public_id": "lucas-a-405643141",
        "tracking_id": "577876613"
    },
    {
        "urn_id": "ACoAACoTSqoBeb3KY-xcNpauP2FzjvtvtnLZ0aw",
        "distance": "DISTANCE_3",
        "public_id": "giovani-milani-2624a7178",
        "tracking_id": "705907370"
    },
    {
        "urn_id": "ACoAABEIL_sBNP2oqYgmi45ooi5b-AGIfR51bKY",
        "distance": "DISTANCE_3",
        "public_id": "natasha-bueno",
        "tracking_id": "285749243"
    },
    {
        "urn_id": "ACoAAA3zLv8BmXTcH-pKm3efbUY08pz0iO11csQ",
        "distance": "DISTANCE_3",
        "public_id": "alessandro-santos-53b46866",
        "tracking_id": "234041087"
    },
    {
        "urn_id": "ACoAACqqKmoBHx9nsJLc_g0RSRmYUnwD0Xi94vc",
        "distance": "DISTANCE_3",
        "public_id": "bruno-leite-2b687517b",
        "tracking_id": "715795050"
    },
    {
        "urn_id": "ACoAAB0vfE4BcirPM42MxLwirInfHqFRB23qtv8",
        "distance": "DISTANCE_3",
        "public_id": "giovanna-gomes-simiguini-012b97117",
        "tracking_id": "489651278"
    },
    {
        "urn_id": "ACoAACGO8rIBBXmDsoK0PWpGv5_JgXCbaT6Ett8",
        "distance": "DISTANCE_3",
        "public_id": "thalitastorel",
        "tracking_id": "563016370"
    },
    {
        "urn_id": "ACoAABNnlIcB7WMRSQi46JDFIzpNuVRrRz2bSMY",
        "distance": "DISTANCE_3",
        "public_id": "nathalia-cardoso-0b304091",
        "tracking_id": "325555335"
    },
    {
        "urn_id": "ACoAABi6YXIBVwqE-QoJgILLHU0k6PHpzKF7tRE",
        "distance": "DISTANCE_3",
        "public_id": "milena-zagarino-ornellas",
        "tracking_id": "414867826"
    },
    {
        "urn_id": "ACoAACJ8660B5gHY41pkfyZKYXZCiS9HdZXVNXk",
        "distance": "DISTANCE_3",
        "public_id": "paula-fernanda-guimarães-ba5938141",
        "tracking_id": "578612141"
    },
    {
        "urn_id": "ACoAABHCMtwBJ1TJTz9v71zlr6cdep4vN83FyCs",
        "distance": "DISTANCE_3",
        "public_id": "flpstrri",
        "tracking_id": "297939676"
    },
    {
        "urn_id": "ACoAACUymM4B5ZPD5z4la6vDiQv2yMp_GOaG8XM",
        "distance": "DISTANCE_3",
        "public_id": "maurício-reis-do-nascimento-37a001155",
        "tracking_id": "624072910"
    },
    {
        "urn_id": "ACoAAAibW3sBSov4eMR-OC45WCOt-ixQqyRJ94Q",
        "distance": "DISTANCE_3",
        "public_id": "carolina-araújo-falcão-44b43840",
        "tracking_id": "144399227"
    },
    {
        "urn_id": "ACoAAAo-32EB_M9d-4VVyt9kykNVqA9PtagQqGc",
        "distance": "DISTANCE_3",
        "public_id": "max-targino-a5569649",
        "tracking_id": "171892577"
    },
    {
        "urn_id": "ACoAACKSJDwBnPOgeLjeMuBp-5CwjZK9CqgCmmo",
        "distance": "DISTANCE_3",
        "public_id": "annaclaramelosouza",
        "tracking_id": "580002876"
    },
    {
        "urn_id": "ACoAAAXP8ToBo_WK3oxC8MzeCDHYwwV8Y5ctugY",
        "distance": "DISTANCE_3",
        "public_id": "thiago-augustini-ux-designer",
        "tracking_id": "97513786"
    },
    {
        "urn_id": "ACoAAAX88oIBilU5GhPx8PV1tQm40W1Y63OxoZ4",
        "distance": "DISTANCE_3",
        "public_id": "amandafonseca",
        "tracking_id": "100463234"
    },
    {
        "urn_id": "ACoAABpTZBEBoW4qYSixmJ-AMQtpA_H_quxywjw",
        "distance": "DISTANCE_3",
        "public_id": "marina-itaborai-servino-781ab9103",
        "tracking_id": "441672721"
    },
    {
        "urn_id": "ACoAABo1aewBpSUhkDWKjUnRzHDzKUza0hEgkss",
        "distance": "DISTANCE_3",
        "public_id": "sabrina-guedes-890310103",
        "tracking_id": "439708140"
    },
    {
        "urn_id": "ACoAACPHSjABIXlQx6Ue_696EnbKTppSbRewZMY",
        "distance": "DISTANCE_3",
        "public_id": "alana-calbente",
        "tracking_id": "600263216"
    },
    {
        "urn_id": "ACoAAARziWgBJ7avG7xQQGeoXjEwSX6xoAk4mLY",
        "distance": "DISTANCE_3",
        "public_id": "camilanloliveira",
        "tracking_id": "74680680"
    },
    {
        "urn_id": "ACoAACSLwP8BFySmDgOUaLTbp1ROhkCcvwQRl-0",
        "distance": "DISTANCE_3",
        "public_id": "camilla-c-767409151",
        "tracking_id": "613138687"
    },
    {
        "urn_id": "ACoAACQPlq4BuXIYr0qe2IiijVJMkuDBBo4JAEQ",
        "distance": "DISTANCE_3",
        "public_id": "milenatsouza",
        "tracking_id": "605001390"
    },
    {
        "urn_id": "ACoAAAM1Dg8BFg4MveiDa9jB3-sm4cglYbsXrZo",
        "distance": "DISTANCE_3",
        "public_id": "guilhermeanchieta",
        "tracking_id": "53808655"
    },
    {
        "urn_id": "ACoAAAaTMGQBV-ouo89SIB5K53bG37zuDYn6DGk",
        "distance": "DISTANCE_3",
        "public_id": "vanessa-alexandre",
        "tracking_id": "110309476"
    },
    {
        "urn_id": "ACoAACwCfKoBC9lZ_juDwAz7PoYsBrU6XJl-IRo",
        "distance": "DISTANCE_3",
        "public_id": "taynã-chiodi",
        "tracking_id": "738360490"
    },
    {
        "urn_id": "ACoAAC1XuncBK1loqowwDBnhAKSRfNaH29c2jEk",
        "distance": "DISTANCE_3",
        "public_id": "juliana-silva-a1b921192",
        "tracking_id": "760724087"
    },
    {
        "urn_id": "ACoAABUJseMBfRLCVG5MBVJhM-p93DfCJ-JDEZU",
        "distance": "DISTANCE_3",
        "public_id": "acvidal",
        "tracking_id": "352956899"
    },
    {
        "urn_id": "ACoAADG-eiYBuyyS2C5yvUAkEvrVMLvjQ4XIHeM",
        "distance": "DISTANCE_3",
        "public_id": "karen-quispe",
        "tracking_id": "834566694"
    },
    {
        "urn_id": "ACoAAA2e2K4BB6yU9hblvf4qWqLSJnQWCGI17a8",
        "distance": "DISTANCE_3",
        "public_id": "victor-alves-a6664164",
        "tracking_id": "228513966"
    },
    {
        "urn_id": "ACoAACr9GDEBhHLzXyY2NEWgLK6Wk_Le81IvTY0",
        "distance": "DISTANCE_3",
        "public_id": "mariana-serrão-ribeiro-495656181",
        "tracking_id": "721229873"
    },
    {
        "urn_id": "ACoAAB2O_hMBbY4DDrHO1WGhf-IqqgeHg_jrqm4",
        "distance": "DISTANCE_3",
        "public_id": "vanessafmuller",
        "tracking_id": "495910419"
    },
    {
        "urn_id": "ACoAAA0Qe4wBtt_PNRDG8w07p3YgQ46aVOxJ8y4",
        "distance": "DISTANCE_3",
        "public_id": "ricardomertens",
        "tracking_id": "219184012"
    },
    {
        "urn_id": "ACoAACEUsCsBqz1mJLgJEewFSpLReecSm77-vcc",
        "distance": "DISTANCE_3",
        "public_id": "mariana-figueiredo-a0ba52135",
        "tracking_id": "555003947"
    },
    {
        "urn_id": "ACoAAC4YPocBcI_0P9l1gC5tViocVH-sSg4Qj8E",
        "distance": "DISTANCE_3",
        "public_id": "giuliamadi",
        "tracking_id": "773340807"
    },
    {
        "urn_id": "ACoAABCYergBm9V5fhRlf2TgyuvH0_OiwAgmKp0",
        "distance": "DISTANCE_3",
        "public_id": "katieli-dieter",
        "tracking_id": "278428344"
    },
    {
        "urn_id": "ACoAABWWx04BNWEeUPsY7t87zhRFpp-jYSsPkGo",
        "distance": "DISTANCE_3",
        "public_id": "luis-felipe-santana-23a374a1",
        "tracking_id": "362202958"
    },
    {
        "urn_id": "ACoAABTvfVwByNH4nGafBWtPNUKD6AOse9nUqbY",
        "distance": "DISTANCE_3",
        "public_id": "flaviamendess",
        "tracking_id": "351239516"
    },
    {
        "urn_id": "ACoAABjDan0BZXka3L9OPYJvO9E_7CXdClyFBjw",
        "distance": "DISTANCE_3",
        "public_id": "victória-luiz-da-silva-279178b7",
        "tracking_id": "415459965"
    },
    {
        "urn_id": "ACoAABavYHkBcBNuuUgxMRQ-LOpTqCAUvWaN8Fc",
        "distance": "DISTANCE_3",
        "public_id": "marcelo-martins-189562a7",
        "tracking_id": "380592249"
    },
    {
        "urn_id": "ACoAACnp7IoBcq2feVac0XaXeuHtCC_aG8L-Tds",
        "distance": "DISTANCE_3",
        "public_id": "luis-guilherme-hermetto-dias-3765ba177",
        "tracking_id": "703196298"
    },
    {
        "urn_id": "ACoAABdLAh0BH9SEzuGCW-kzJMVtsCkcUWoKObA",
        "distance": "DISTANCE_3",
        "public_id": "luam-barros",
        "tracking_id": "390791709"
    },
    {
        "urn_id": "ACoAABfsM8oBU5j9jylP8iHSIpcYbl4ODc-jXw0",
        "distance": "DISTANCE_3",
        "public_id": "victoriacheberle",
        "tracking_id": "401355722"
    },
    {
        "urn_id": "ACoAACQdxOIBQNJTH8pXkIY-J_s7QOq9bEPrpOU",
        "distance": "DISTANCE_3",
        "public_id": "marcilene-cavalcanti-42ab1214a",
        "tracking_id": "605930722"
    },
    {
        "urn_id": "ACoAAAnU6F8Bo0vwyHxMENq6zfHbkIL8PyJcbEE",
        "distance": "DISTANCE_3",
        "public_id": "kelliguidolini",
        "tracking_id": "164948063"
    },
    {
        "urn_id": "ACoAACGZCKkBaT_1P8UlH8ricosBYpkUNDSe7KY",
        "distance": "DISTANCE_3",
        "public_id": "rodrigo-das-neves-martins-209936138",
        "tracking_id": "563677353"
    },
    {
        "urn_id": "ACoAABFqW10BpLDvdNekSR7oFaVwOgTW-kGopNI",
        "distance": "DISTANCE_3",
        "public_id": "nigliar",
        "tracking_id": "292182877"
    },
    {
        "urn_id": "ACoAAAcUm0kBMjyvUypkDEdR5bzNt_yaeudMhRQ",
        "distance": "DISTANCE_3",
        "public_id": "eduardoaarce",
        "tracking_id": "118790985"
    },
    {
        "urn_id": "ACoAAAiUuLIBiQe3fMHhFx8v5lA4p96e3QyKlTQ",
        "distance": "DISTANCE_3",
        "public_id": "eliasfernandes",
        "tracking_id": "143964338"
    },
    {
        "urn_id": "ACoAAATJyq0B7dUzSMrFRwi0Z8qqYtnOHHY86Fo",
        "distance": "DISTANCE_3",
        "public_id": "rodrigo-estrela",
        "tracking_id": "80333485"
    },
    {
        "urn_id": "ACoAAAroESABYEvL-vZhUW_fQLg1JwlrQinB1sM",
        "distance": "DISTANCE_3",
        "public_id": "isabelaem",
        "tracking_id": "182980896"
    },
    {
        "urn_id": "ACoAABXJ8kgB1jEyA5JIWH-_USzcbot5YicID_4",
        "distance": "DISTANCE_3",
        "public_id": "gustagaspar",
        "tracking_id": "365556296"
    },
    {
        "urn_id": "ACoAAA14ReoBHonWWxgcf0Rw3QSyOmR15-ZOHQg",
        "distance": "DISTANCE_3",
        "public_id": "karoline-dantas-peixoto-b4a82263",
        "tracking_id": "225986026"
    },
    {
        "urn_id": "ACoAAAfTvJkBBi9qpCLmgSqBoCm-RDM1uOITiJk",
        "distance": "DISTANCE_3",
        "public_id": "simone-morales-6a1b8937",
        "tracking_id": "131316889"
    },
    {
        "urn_id": "ACoAABovBpoBBkcfvQ7eE_iwPfhQjNr9AYPpZ1c",
        "distance": "DISTANCE_3",
        "public_id": "augusto-zanetti",
        "tracking_id": "439289498"
    },
    {
        "urn_id": "ACoAACcT2MIBndjCgTI_g4-MSIKiMgSaPCDVsCA",
        "distance": "DISTANCE_3",
        "public_id": "michele-pereira-196691163",
        "tracking_id": "655612098"
    },
    {
        "urn_id": "ACoAACpl6kIBYmH_ZzdXp53cBoIy1nozAah-qI4",
        "distance": "DISTANCE_3",
        "public_id": "alana-lima",
        "tracking_id": "711322178"
    },
    {
        "urn_id": "ACoAAAso_NABVBfYbPMtcQupnmXrYUWx9WizTtQ",
        "distance": "DISTANCE_3",
        "public_id": "felipe-nogueira-a9485552",
        "tracking_id": "187235536"
    },
    {
        "urn_id": "ACoAAABGnGkBBiySdGSIfwyZuMs-pLHdodBOZLk",
        "distance": "DISTANCE_3",
        "public_id": "rodolfo-chung-ba16711",
        "tracking_id": "4627561"
    },
    {
        "urn_id": "ACoAABTG0FoBn5_Cbg022FYvR25EBzhJO5EV79o",
        "distance": "DISTANCE_3",
        "public_id": "lucas-cordeiro-oliveira",
        "tracking_id": "348573786"
    },
    {
        "urn_id": "ACoAAAsJEJMBs12dbxMUpsFbZIf4-cm_3x0r1Fw",
        "distance": "DISTANCE_3",
        "public_id": "sergio-fernandes-24300752",
        "tracking_id": "185143443"
    },
    {
        "urn_id": "ACoAAB9CftQBfKPCV8U1PO1oPtxwr-bZj0pyZKk",
        "distance": "DISTANCE_3",
        "public_id": "jsalgues",
        "tracking_id": "524451540"
    },
    {
        "urn_id": "ACoAACDO4fkB7oJ-nR0SC3hHvN1cBQbOC_6jrfs",
        "distance": "DISTANCE_3",
        "public_id": "jeferson-alves-4a1407134",
        "tracking_id": "550429177"
    },
    {
        "urn_id": "ACoAAAVNXC4Br9peYUOY62ozIay2cwp_OTsWHps",
        "distance": "DISTANCE_3",
        "public_id": "michelle-paiva-17a95b25",
        "tracking_id": "88955950"
    },
    {
        "urn_id": "ACoAAAbdCDgBDOJ1-0nCuNL8ULEfrdUor-FKrJ4",
        "distance": "DISTANCE_3",
        "public_id": "icaroribeiro",
        "tracking_id": "115148856"
    },
    {
        "urn_id": "ACoAACVz0bgB-HM6epnSp8ryiyiiFZLSgFTm8zQ",
        "distance": "DISTANCE_3",
        "public_id": "gabriela-etavares",
        "tracking_id": "628347320"
    },
    {
        "urn_id": "ACoAAAvZoikB8CiJOCcUoKe9wHWsM45-jtvUBPM",
        "distance": "DISTANCE_3",
        "public_id": "edgardvidalf",
        "tracking_id": "198812201"
    },
    {
        "urn_id": "ACoAAAlXY_UB2Qr2pPUDcYNv2PnefUcZSnVs3qs",
        "distance": "DISTANCE_3",
        "public_id": "julianaloures",
        "tracking_id": "156722165"
    },
    {
        "urn_id": "ACoAAC0-7HAB7NVZADGamJzt7Cne5hNecwiKsj8",
        "distance": "DISTANCE_3",
        "public_id": "leonardo-mantovaneli",
        "tracking_id": "759098480"
    },
    {
        "urn_id": "ACoAAAtWcksBUPs1DqIv4TO5B48uLTPohbKrOzM",
        "distance": "DISTANCE_3",
        "public_id": "bruno-dorota-andretto-b7785153",
        "tracking_id": "190214731"
    },
    {
        "urn_id": "ACoAAAaNcYoBXeqmHvDiIa6lovwSKcfVDuuF_EI",
        "distance": "DISTANCE_3",
        "public_id": "marianafabio",
        "tracking_id": "109932938"
    },
    {
        "urn_id": "ACoAAC8dwj8BHrrTYEUrwR_Gut9aYG81d5d5p6Q",
        "distance": "DISTANCE_3",
        "public_id": "lorraine-quintino-4538911a0",
        "tracking_id": "790479423"
    },
    {
        "urn_id": "ACoAAB3xAUgBUygkpKQr7xft3tpjLG5i0yNWLz8",
        "distance": "DISTANCE_3",
        "public_id": "mateus-porto",
        "tracking_id": "502333768"
    },
    {
        "urn_id": "ACoAABZdIxkBlEK8M4aYZquZco9axiW9ft1DIZs",
        "distance": "DISTANCE_3",
        "public_id": "danielcyamato",
        "tracking_id": "375202585"
    },
    {
        "urn_id": "ACoAABYppB0Bbe_D8athynS1dt5dTjoI_0SGVOo",
        "distance": "DISTANCE_3",
        "public_id": "jack-romao",
        "tracking_id": "371827741"
    },
    {
        "urn_id": "ACoAABKo-wsBN47OcjOOKaVg48y8ri4XLXRoaLU",
        "distance": "DISTANCE_3",
        "public_id": "gustavo-szauter-4b7a1788",
        "tracking_id": "313064203"
    },
    {
        "urn_id": "ACoAAALOv9oB86tPZG1OMnJTyWof3Vk5vzaFeHg",
        "distance": "DISTANCE_3",
        "public_id": "regis-tavares-2a293713",
        "tracking_id": "47103962"
    },
    {
        "urn_id": "ACoAACV0vREBuATnISgykXjMRKxNPz4VyZHuZvY",
        "distance": "DISTANCE_3",
        "public_id": "jessyca-lima-melo",
        "tracking_id": "628407569"
    },
    {
        "urn_id": "ACoAACGgRrUBvuhzaZ481ab05hCCM-UZEL0fReA",
        "distance": "DISTANCE_3",
        "public_id": "lucas-ombarbosa",
        "tracking_id": "564151989"
    },
    {
        "urn_id": "ACoAACpKLCMBbECp2LdYz1HNCD89Tnng1FxDeG8",
        "distance": "DISTANCE_3",
        "public_id": "larissasloppes",
        "tracking_id": "709504035"
    },
    {
        "urn_id": "ACoAABqBOZ4BVbLYXXpjUFy4piVtr9RFKF_oXfQ",
        "distance": "DISTANCE_3",
        "public_id": "thiago-rsantos",
        "tracking_id": "444676510"
    },
    {
        "urn_id": "ACoAACQPYwMBj7c-qG9PJcMVB-D-ISD8Pln94n8",
        "distance": "DISTANCE_3",
        "public_id": "jefferson-soares-da-rocha-a8373814a",
        "tracking_id": "604988163"
    },
    {
        "urn_id": "ACoAADF-RpMBdK74Dt96vb14NQKFivwhwaSq4CY",
        "distance": "DISTANCE_3",
        "public_id": "ana-carolina-pozzan-vetorazo-b2b1031b2",
        "tracking_id": "830359187"
    },
    {
        "urn_id": "ACoAAB-PhAkBZsR4TRBeqXGkKL1r2mMX-2ZMFjM",
        "distance": "DISTANCE_3",
        "public_id": "gersonlucemo",
        "tracking_id": "529499145"
    },
    {
        "urn_id": "ACoAAAgopQ8BhS9MMeHEU9Gu4EpC3cXinV2WGIQ",
        "distance": "DISTANCE_3",
        "public_id": "tamyponczyk",
        "tracking_id": "136881423"
    },
    {
        "urn_id": "ACoAAB2od7AB8MHK-Dh_wvzVAaPPmQI8KoR1aY0",
        "distance": "DISTANCE_3",
        "public_id": "ricksouza1992",
        "tracking_id": "497579952"
    },
    {
        "urn_id": "ACoAACILQ3MBjw1JErMDw8LDfmboI-_DUey2JZU",
        "distance": "DISTANCE_3",
        "public_id": "daniel-meshulam-ajzental-52b34613b",
        "tracking_id": "571163507"
    },
    {
        "urn_id": "ACoAAAW0DioBJri2BDO_6bGRhKa1H7DI6W4HVtU",
        "distance": "DISTANCE_3",
        "public_id": "lfernandocardoso",
        "tracking_id": "95686186"
    },
    {
        "urn_id": "ACoAAAo7G1kBcgerwSHoagMV-4YfqitjkGT1uws",
        "distance": "DISTANCE_3",
        "public_id": "diego-felipe-lisboa-07559849",
        "tracking_id": "171645785"
    },
    {
        "urn_id": "ACoAACJNnjIB8LEtUVKCT4HoVhaO4ja_idI8C1k",
        "distance": "DISTANCE_3",
        "public_id": "marco-antonio-martin-ferri-baa8a2140",
        "tracking_id": "575512114"
    },
    {
        "urn_id": "ACoAAAcqKAcB4Gt9ZJHSQM7xZWmo40Fa8n7kznQ",
        "distance": "DISTANCE_3",
        "public_id": "dorodrigues",
        "tracking_id": "120203271"
    },
    {
        "urn_id": "ACoAACojeD4B2VzRse217BZi5RXCij3ikZKFJeM",
        "distance": "DISTANCE_3",
        "public_id": "lucasdvaz",
        "tracking_id": "706967614"
    },
    {
        "urn_id": "ACoAADBmVS8BUwXZN6F0N3Q6oHMvpwa_Et_xKG8",
        "distance": "DISTANCE_3",
        "public_id": "matheus-sodre-duarte-pereira",
        "tracking_id": "812012847"
    },
    {
        "urn_id": "ACoAAAK3fFIBXoBKBZHc05-1uVAcekZWHaJ3JaA",
        "distance": "DISTANCE_2",
        "public_id": "luciane-destro",
        "tracking_id": "45579346"
    },
    {
        "urn_id": "ACoAABBHLtMBZ-FzMkDeLfb6CdMqAC85YJCsjss",
        "distance": "DISTANCE_2",
        "public_id": "lfernandoguedes",
        "tracking_id": "273100499"
    },
    {
        "urn_id": "ACoAABt_idUBOks8QO-M6M7CNfmNP21VZocarQc",
        "distance": "DISTANCE_3",
        "public_id": "thaís-martini-pereira-01960510a",
        "tracking_id": "461343189"
    },
    {
        "urn_id": "ACoAAAtSs2IBqucPTltRANXTxUDi6uKxp8XaTHw",
        "distance": "DISTANCE_2",
        "public_id": "fernando-gabriel-tomaz-souza-aaa75353",
        "tracking_id": "189969250"
    },
    {
        "urn_id": "ACoAAAT4dEYB7twv4UGnNUdkm6L0uI-xlycvwwA",
        "distance": "DISTANCE_2",
        "public_id": "cezarpavelski",
        "tracking_id": "83391558"
    },
    {
        "urn_id": "ACoAAB85oYcBBPuecAeCbQbzuvv2IEB9UVP6r5s",
        "distance": "DISTANCE_3",
        "public_id": "raqueldecassiasc",
        "tracking_id": "523870599"
    },
    {
        "urn_id": "ACoAABY25u8BoOCGF_FzfTpemT-QSxh6Lxcv164",
        "distance": "DISTANCE_3",
        "public_id": "pedro-ribeiro-03b995a4",
        "tracking_id": "372696815"
    },
    {
        "urn_id": "ACoAACHEfW4BqSAf80BZ3ho5bpSal8akehCmd14",
        "distance": "DISTANCE_3",
        "public_id": "patrícia-rezende-35288a139",
        "tracking_id": "566525294"
    },
    {
        "urn_id": "ACoAABwOV1UBlitmhEhokHn_qnaePJeeGxU-Wr0",
        "distance": "DISTANCE_3",
        "public_id": "lucas-balthazar-b31778111",
        "tracking_id": "470701909"
    },
    {
        "urn_id": "ACoAAAvrKTMB0OSR1aVZW4tLE8dqeLSM1yB-aus",
        "distance": "DISTANCE_3",
        "public_id": "caiofattori",
        "tracking_id": "199960883"
    },
    {
        "urn_id": "ACoAABDahOEB1NckZAo4kOkX_3ncqICE0BYz0Uo",
        "distance": "DISTANCE_3",
        "public_id": "bruno-goulart-ribeiro-1698407a",
        "tracking_id": "282756321"
    },
    {
        "urn_id": "ACoAAB1jdfsBuARRxiQdvjEtE5v1uglgq4CmU6w",
        "distance": "DISTANCE_3",
        "public_id": "pldomingues",
        "tracking_id": "493057531"
    },
    {
        "urn_id": "ACoAAC1vbf8By8HoBfAsC7Jl6NwsqntG6gGx0as",
        "distance": "DISTANCE_3",
        "public_id": "bruna-mendonça-rezende-8a7350193",
        "tracking_id": "762277375"
    },
    {
        "urn_id": "ACoAAAWBjmYBjg6DTbUttl_o2JN2frUTl8cX1oU",
        "distance": "DISTANCE_3",
        "public_id": "giovani-mombelli-mussio",
        "tracking_id": "92376678"
    },
    {
        "urn_id": "ACoAADI0nQ8BR4DYykCw2MslMmBycPJuMb9G4Wc",
        "distance": "DISTANCE_3",
        "public_id": "rupesh-lokhande-3271071b6",
        "tracking_id": "842308879"
    },
    {
        "urn_id": "ACoAACJTJowBZh7YI68Wz_hgrKtdOLstN4_rh_Q",
        "distance": "DISTANCE_3",
        "public_id": "patriciasalla",
        "tracking_id": "575874700"
    },
    {
        "urn_id": "ACoAACfFbqgBeDl1k-wPYdkJ7vS6SRZt0D9788M",
        "distance": "DISTANCE_3",
        "public_id": "livia-leite",
        "tracking_id": "667250344"
    },
    {
        "urn_id": "ACoAACzhl5QBZjXoqSCxwCX453qQuhDcC5fNOdw",
        "distance": "DISTANCE_3",
        "public_id": "igor-almeida-504209190",
        "tracking_id": "752981908"
    },
    {
        "urn_id": "ACoAADFGHwsBZ6TbOk00188M2MO3pKYwcFgFz0Q",
        "distance": "DISTANCE_3",
        "public_id": "yuri-antonio-28ba2a1b0",
        "tracking_id": "826679051"
    },
    {
        "urn_id": "ACoAACLW6MoBEOgzu9pV17COwV2URgdbtJeWd20",
        "distance": "DISTANCE_3",
        "public_id": "bárbara-martino",
        "tracking_id": "584509642"
    },
    {
        "urn_id": "ACoAAAov86MBTDVxyfA6nit9gQKuweVs0jITr4U",
        "distance": "DISTANCE_3",
        "public_id": "luise-rios",
        "tracking_id": "170914723"
    },
    {
        "urn_id": "ACoAACghi2oBWtwgiGG79WaLSolxlGtlBRvxQMI",
        "distance": "DISTANCE_3",
        "public_id": "belaavellar",
        "tracking_id": "673287018"
    },
    {
        "urn_id": "ACoAACfflg8BnB-Soyy0csNYWDEg24WvRwHuAcw",
        "distance": "DISTANCE_3",
        "public_id": "paula-bortoletto-1a7050168",
        "tracking_id": "668964367"
    },
    {
        "urn_id": "ACoAACga_oYBiSQ6lunjcQERtqomzkTbXb9OyNs",
        "distance": "DISTANCE_3",
        "public_id": "cirovieirajr",
        "tracking_id": "672857734"
    },
    {
        "urn_id": "ACoAABjgM1oBSQTlrUvZTWy8ZEGbXHlofAW4ljo",
        "distance": "DISTANCE_3",
        "public_id": "isabelapnt",
        "tracking_id": "417346394"
    },
    {
        "urn_id": "ACoAACqzMlUBhDrCzLD6572YT5Jo_imorDTmAls",
        "distance": "DISTANCE_3",
        "public_id": "gabrieltaveira",
        "tracking_id": "716386901"
    },
    {
        "urn_id": "ACoAAAqqVUABXGa10nOZ1uUNZ8xPhuXrQDS7I2E",
        "distance": "DISTANCE_3",
        "public_id": "cesar-lemos-4a8b124b",
        "tracking_id": "178935104"
    },
    {
        "urn_id": "ACoAAAn0ffoBe4ti-tVm6bE9zw1CsbH5HFR75iM",
        "distance": "DISTANCE_3",
        "public_id": "leonardo-chapoñan-benavente-b0ab2547",
        "tracking_id": "167017978"
    },
    {
        "urn_id": "ACoAAChSBfQBTMHzfBYYAED3jAauqHamax8y758",
        "distance": "DISTANCE_3",
        "public_id": "nadia-santos",
        "tracking_id": "676464116"
    },
    {
        "urn_id": "ACoAADEUo4oB90AlEGv9YEsUpVILQgwGxyPbZTg",
        "distance": "DISTANCE_3",
        "public_id": "breno-faria-68a9251ab",
        "tracking_id": "823436170"
    },
    {
        "urn_id": "ACoAABncj9MBnUsOrFKuJPfCNmtG2ZiBrHOIgO0",
        "distance": "DISTANCE_3",
        "public_id": "izabella-borges-b2b382101",
        "tracking_id": "433885139"
    },
    {
        "urn_id": "ACoAAAUMsl0BNltnygfv2CpEukSYxjbBlB-b9rU",
        "distance": "DISTANCE_3",
        "public_id": "manuauge",
        "tracking_id": "84718173"
    },
    {
        "urn_id": "ACoAAAzJjTgBe8_8DZZnYHvZ-2IF95OtwipxkRE",
        "distance": "DISTANCE_3",
        "public_id": "keoma-mota-588a205b",
        "tracking_id": "214535480"
    },
    {
        "urn_id": "ACoAACm73osBGYxtl7Hq7e0ZPulXS5uoxA3UVHw",
        "distance": "DISTANCE_3",
        "public_id": "italocosta23",
        "tracking_id": "700178059"
    },
    {
        "urn_id": "ACoAABJMPS4BYL15923QkVIWzk1K6aa6sGeD7z8",
        "distance": "DISTANCE_3",
        "public_id": "andré-medina-12698686",
        "tracking_id": "306986286"
    },
    {
        "urn_id": "ACoAAA3EsG0BRaz_EHFF_ipyfVrSRKVXIF-eR_Y",
        "distance": "DISTANCE_3",
        "public_id": "willian-amorim-12543965",
        "tracking_id": "230994029"
    },
    {
        "urn_id": "ACoAABT48GsBxttIyAGon_yQLXQHG4XAHZ-Myrs",
        "distance": "DISTANCE_3",
        "public_id": "moisescl",
        "tracking_id": "351858795"
    },
    {
        "urn_id": "ACoAACD6yawBiE4I1KWNx7OtfBDbmBH8zGPldMU",
        "distance": "DISTANCE_3",
        "public_id": "lucaschagasribeiro",
        "tracking_id": "553306540"
    },
    {
        "urn_id": "ACoAAAs_y_0BFmuNzR3uuDlnR9mptwOi_0DCfaw",
        "distance": "DISTANCE_3",
        "public_id": "mateus-silva-carvalho",
        "tracking_id": "188730365"
    },
    {
        "urn_id": "ACoAABD73GABAC6_8WRxlXR1P4I0GXe9ZXaTe2Y",
        "distance": "DISTANCE_3",
        "public_id": "caiobraz-engenheiro",
        "tracking_id": "284941408"
    },
    {
        "urn_id": "ACoAABm2WW4BPQNyeiNd2d1GNa4Fe8g5mcnsQiM",
        "distance": "DISTANCE_3",
        "public_id": "thaís-araújo",
        "tracking_id": "431380846"
    },
    {
        "urn_id": "ACoAACd8m74B2Icf5xZhxN2TI5mt28jkdJVnR5E",
        "distance": "DISTANCE_3",
        "public_id": "açucena-carisio-3baa42165",
        "tracking_id": "662477758"
    },
    {
        "urn_id": "ACoAAB_9RdkBA3xmCNXUqxlx4OokyiP2H0Vt6mc",
        "distance": "DISTANCE_3",
        "public_id": "carolina-morela",
        "tracking_id": "536692185"
    },
    {
        "urn_id": "ACoAABhotB8Baz3GK_JvfKVadU3nxRbTIOsKGhc",
        "distance": "DISTANCE_3",
        "public_id": "isabelastorres",
        "tracking_id": "409515039"
    },
    {
        "urn_id": "ACoAABz34mMBuLzBme4dw9Cksub-jtiF3EVu4Oc",
        "distance": "DISTANCE_3",
        "public_id": "amanda-fiaes-34391a116",
        "tracking_id": "486007395"
    },
    {
        "urn_id": "ACoAACpqmbgB4bwcES__EsbyA6Ts67CkBCz3Nxo",
        "distance": "DISTANCE_3",
        "public_id": "eduardo-felix-5883a617a",
        "tracking_id": "711629240"
    },
    {
        "urn_id": "ACoAABVisvMBXeZZoEts3xviBc2pG1DMO0SPxdU",
        "distance": "DISTANCE_3",
        "public_id": "giovannadillio",
        "tracking_id": "358789875"
    },
    {
        "urn_id": "ACoAAB9drZsBunktTkicG93GviPL3MWQhRu0bf8",
        "distance": "DISTANCE_3",
        "public_id": "silasabud",
        "tracking_id": "526232987"
    },
    {
        "urn_id": "ACoAABVHFB0Bvo9TSF1KMcHOxVFNwpCUkYTY1Xw",
        "distance": "DISTANCE_3",
        "public_id": "cesarferrinha",
        "tracking_id": "356979741"
    },
    {
        "urn_id": "ACoAABxwGqcBfa3TQKAf_ggIJihyq6knMBh6oec",
        "distance": "DISTANCE_3",
        "public_id": "lorena-lavalle-alves-silva-833948113",
        "tracking_id": "477108903"
    },
    {
        "urn_id": "ACoAABrhtH8B4exIuadNRU1oJzLLYQo48haSi5E",
        "distance": "DISTANCE_3",
        "public_id": "mariahmmoreira",
        "tracking_id": "450999423"
    },
    {
        "urn_id": "ACoAACMxCqkB9YJ7J4JlHsyigpE9czfZ6ZrNNKo",
        "distance": "DISTANCE_3",
        "public_id": "erika-calixto-antonio-2b5890145",
        "tracking_id": "590416553"
    },
    {
        "urn_id": "ACoAAC4DvikBkzCTADRjtoRtXXW1rV-IABoeAcY",
        "distance": "DISTANCE_3",
        "public_id": "isabelacardia",
        "tracking_id": "771997225"
    },
    {
        "urn_id": "ACoAABvTqUQBBzWT9b-3TMXHJKHe34ipHF-3hB4",
        "distance": "DISTANCE_3",
        "public_id": "rodrigo-cmichel",
        "tracking_id": "466856260"
    },
    {
        "urn_id": "ACoAAASivBkBO8nC4h19t0pDTeLwlof0sfdsoAg",
        "distance": "DISTANCE_3",
        "public_id": "igor-smendes",
        "tracking_id": "77773849"
    },
    {
        "urn_id": "ACoAABDy-doBtiYN2gmVxZ5tl7QM3ogUNEY2F0A",
        "distance": "DISTANCE_3",
        "public_id": "marcos-vinicius-8222937b",
        "tracking_id": "284359130"
    },
    {
        "urn_id": "ACoAAAq-O9IBtmCFmb1dex4Epn4ZYINtKBk4k_8",
        "distance": "DISTANCE_3",
        "public_id": "mauro-lopes-1aa44150",
        "tracking_id": "180239314"
    },
    {
        "urn_id": "ACoAACLu13ABMd6usn1hiJjWvOnKfA9JozcFTho",
        "distance": "DISTANCE_3",
        "public_id": "paulo-nascimento-668339144",
        "tracking_id": "586078064"
    },
    {
        "urn_id": "ACoAAB86bsMB2dvQv220ySUDR_CIsIwuTvVngSw",
        "distance": "DISTANCE_3",
        "public_id": "laurakuser",
        "tracking_id": "523923139"
    },
    {
        "urn_id": "ACoAABNuTG0BJVNSG2VHcQUcdDO5O4pep0U_fqY",
        "distance": "DISTANCE_3",
        "public_id": "alyne-berger",
        "tracking_id": "325995629"
    },
    {
        "urn_id": "ACoAAAcaSjQBTDKKwV8w0mnu7z6YFvEKMeyC3H0",
        "distance": "DISTANCE_3",
        "public_id": "ana-yumi-bezerra",
        "tracking_id": "119163444"
    },
    {
        "urn_id": "ACoAAACwiokB2nKUts9-2rZaww5iHssfFnsTvac",
        "distance": "DISTANCE_3",
        "public_id": "fghbittencourt",
        "tracking_id": "11569801"
    },
    {
        "urn_id": "ACoAAAHOvQ0BqSMyS4wneYLBNyha8PsbiwYD5tE",
        "distance": "DISTANCE_3",
        "public_id": "vitor-vitorasso-9511a5a",
        "tracking_id": "30326029"
    },
    {
        "urn_id": "ACoAACKyoQkBUn6e9Y_Y0c-BJC8l7pfpLOtl2Jw",
        "distance": "DISTANCE_3",
        "public_id": "clayton-cascais-b21b55142",
        "tracking_id": "582131977"
    },
    {
        "urn_id": "ACoAABC6DdkB6qJa1R348iVMKrwBBDtxLLiBh2o",
        "distance": "DISTANCE_3",
        "public_id": "guilherme-lebelson",
        "tracking_id": "280628697"
    },
    {
        "urn_id": "ACoAABKxSmUBCRmHQMJY5OacJz8VVd-4jJGS4CE",
        "distance": "DISTANCE_3",
        "public_id": "marinmatos",
        "tracking_id": "313608805"
    },
    {
        "urn_id": "ACoAABPaTSEB5cw2m099kI7PXUdZUzPyF5sNTqE",
        "distance": "DISTANCE_3",
        "public_id": "aline-beviláqua",
        "tracking_id": "333073697"
    },
    {
        "urn_id": "ACoAABBeZgYBovN2QzfzUl0URV7IraBjyoFCzZY",
        "distance": "DISTANCE_3",
        "public_id": "caio-benedetti90",
        "tracking_id": "274621958"
    },
    {
        "urn_id": "ACoAAAlpJUgB8m1TWBen_ZB3vP2fsxUkPazse9c",
        "distance": "DISTANCE_3",
        "public_id": "wesleycoder",
        "tracking_id": "157885768"
    },
    {
        "urn_id": "ACoAABuGI_IBzKVN31HZKqdi5COvKeXum34o5LY",
        "distance": "DISTANCE_3",
        "public_id": "claucoelho",
        "tracking_id": "461775858"
    },
    {
        "urn_id": "ACoAADOfqCYB3DCtYVbqnlY1o7bDoufP9fU8mMU",
        "distance": "DISTANCE_3",
        "public_id": "brenda-lulu-032080202",
        "tracking_id": "866101286"
    },
    {
        "urn_id": "ACoAABy2FIgBiKkkJ_OLYkjtmeLxEkh2InESUVU",
        "distance": "DISTANCE_3",
        "public_id": "gustavohmachado",
        "tracking_id": "481694856"
    },
    {
        "urn_id": "ACoAADA2-jQBF_chCgaBr3WLPPshieWdYGdTPGg",
        "distance": "DISTANCE_3",
        "public_id": "luísa-braga-a18a9a1a6",
        "tracking_id": "808909364"
    },
    {
        "urn_id": "ACoAAABeY-oBSx-7jmAkurtDGQdJ6EKCWnI9N6U",
        "distance": "DISTANCE_3",
        "public_id": "guilherme-vaisman-a0a0a32",
        "tracking_id": "6185962"
    },
    {
        "urn_id": "ACoAACIWFokBrarT--CVyJsDdqtH4RYasjx8X1c",
        "distance": "DISTANCE_3",
        "public_id": "laudlemos",
        "tracking_id": "571872905"
    },
    {
        "urn_id": "ACoAACocyeQBTkN6LqI0g-OylEKmhbEZseZJ5rQ",
        "distance": "DISTANCE_3",
        "public_id": "aline-zenha-484747178",
        "tracking_id": "706529764"
    },
    {
        "urn_id": "ACoAACTG9kEB-PBrVpa2FMks2AXeW9ZI61NjeDk",
        "distance": "DISTANCE_3",
        "public_id": "manuella-portilho",
        "tracking_id": "617018945"
    },
    {
        "urn_id": "ACoAABXawE4BQ0RVyuKZSKkADtrDVKYXrMcg35w",
        "distance": "DISTANCE_3",
        "public_id": "luiz-pessoa-152962a2",
        "tracking_id": "366657614"
    },
    {
        "urn_id": "ACoAAA5fTW0BADrb7ytjg-7d0nPtANT3NfB3Dag",
        "distance": "DISTANCE_3",
        "public_id": "felipe-cunha-b5190468",
        "tracking_id": "241126765"
    },
    {
        "urn_id": "ACoAACMJwFUBdWYUu3dkDltldiDDsRHy6xz7nUY",
        "distance": "DISTANCE_3",
        "public_id": "lucas-lfs",
        "tracking_id": "587841621"
    },
    {
        "urn_id": "ACoAAA8syZIBcuyO3eWlOzCYiWqeua1LgxUiOYk",
        "distance": "DISTANCE_3",
        "public_id": "gustavomesquita",
        "tracking_id": "254593426"
    },
    {
        "urn_id": "ACoAAAk7g9IBXtXaa38HD5IMnVpwhCzcjDWGInQ",
        "distance": "DISTANCE_3",
        "public_id": "pedro-henrique-macedo-kumaira",
        "tracking_id": "154895314"
    },
    {
        "urn_id": "ACoAAB5NvfIB3ZrCQy_-UwVkBiJJJ3RYXTlLVs8",
        "distance": "DISTANCE_3",
        "public_id": "mateussanferraz",
        "tracking_id": "508411378"
    },
    {
        "urn_id": "ACoAABoqdOgBD5dn5HE2zwptRzwmv6v9zmgwFGI",
        "distance": "DISTANCE_3",
        "public_id": "anacarlazventurin",
        "tracking_id": "438990056"
    },
    {
        "urn_id": "ACoAAB90YqQBqNadGCTUBx2gHBzzM0fuun97SGI",
        "distance": "DISTANCE_3",
        "public_id": "gabriel-ferreira-204896128",
        "tracking_id": "527721124"
    },
    {
        "urn_id": "ACoAAB_QSOgB0TGns2jFuC2-mwxnBgzm8lCeuuU",
        "distance": "DISTANCE_3",
        "public_id": "ana-julia-roveri-6608bb12a",
        "tracking_id": "533743848"
    },
    {
        "urn_id": "ACoAAAqXS0YB5lVNz9Sy2ALm2hBt_6ev63UO3qk",
        "distance": "DISTANCE_3",
        "public_id": "liryanne",
        "tracking_id": "177687366"
    },
    {
        "urn_id": "ACoAABspwrQBs6jw-zN82e-1lKILrOuFh6HwnY0",
        "distance": "DISTANCE_3",
        "public_id": "allan-gobbo-984753108",
        "tracking_id": "455721652"
    },
    {
        "urn_id": "ACoAACcAlskBwTnoyTn-DSJ18AcTnOzczvtGu1Q",
        "distance": "DISTANCE_3",
        "public_id": "natalia-padilha",
        "tracking_id": "654350025"
    },
    {
        "urn_id": "ACoAADE0RUIB6kDJYQkuMODolanY3eWFjgiwbfM",
        "distance": "DISTANCE_3",
        "public_id": "francielle-viana-2825651b0",
        "tracking_id": "825509186"
    },
    {
        "urn_id": "ACoAAAkJEnwBzjOlgfiN-FWa6d2bPLq9FFdhMjs",
        "distance": "DISTANCE_3",
        "public_id": "camila-carvalho-passos",
        "tracking_id": "151589500"
    },
    {
        "urn_id": "ACoAADWYqfUBz3LDgcAONbpYsMS8A-sEv1QZCfs",
        "distance": "DISTANCE_3",
        "public_id": "lohan-mariano-a71180211",
        "tracking_id": "899197429"
    },
    {
        "urn_id": "ACoAAAU0F5cBb1ZJn4xQwPjOts9C-5TXcihuiAk",
        "distance": "DISTANCE_3",
        "public_id": "rafael-szarf-9b32a025",
        "tracking_id": "87299991"
    },
    {
        "urn_id": "ACoAAB1z3Y8BWQjbBnlNeV3NF-8Eqfg2mUSn3XI",
        "distance": "DISTANCE_3",
        "public_id": "freitasvinicius",
        "tracking_id": "494132623"
    },
    {
        "urn_id": "ACoAACzzvA8BSZiy9mSI8OZcH_5-OsSvtblCFMA",
        "distance": "DISTANCE_3",
        "public_id": "olayres-abreu-5a76a1190",
        "tracking_id": "754170895"
    },
    {
        "urn_id": "ACoAAA9_pOEBeuOv65RBpjeqyv5j5OMKyiNjlOk",
        "distance": "DISTANCE_3",
        "public_id": "jakeline-oliveira-6a90b873",
        "tracking_id": "260023521"
    },
    {
        "urn_id": "ACoAAAcxUxUB2L5HLy4ES9ggY-pvC722RkKAZbs",
        "distance": "DISTANCE_3",
        "public_id": "wellington-bachot-b314b534",
        "tracking_id": "120673045"
    },
    {
        "urn_id": "ACoAACQ7HfsB4KiZZXhTeEFS7BawQdBLwY2A2X8",
        "distance": "DISTANCE_3",
        "public_id": "gabriela-de-sena-cardoso-4a369b14b",
        "tracking_id": "607854075"
    },
    {
        "urn_id": "ACoAABpgVskBZRKDT2ELFETT3dwOUbp-3OdZDbU",
        "distance": "DISTANCE_3",
        "public_id": "leonardo-trindade-martines-861248104",
        "tracking_id": "442521289"
    },
    {
        "urn_id": "ACoAADKU26ABeJk91InhXNNlvbTNBBhFFCqb9Oc",
        "distance": "DISTANCE_3",
        "public_id": "guilherme-microni-5142491b8",
        "tracking_id": "848616352"
    },
    {
        "urn_id": "ACoAAASUgI4BNzwwK2G2jRXdkNGLV3J0RS4XzuU",
        "distance": "DISTANCE_3",
        "public_id": "humberto-mariano-de-carvalho-29289821",
        "tracking_id": "76841102"
    },
    {
        "urn_id": "ACoAAB1I_REBj92Jks72Rq-goPjg0WmbGaoNavA",
        "distance": "DISTANCE_3",
        "public_id": "yannickfinkler",
        "tracking_id": "491322641"
    },
    {
        "urn_id": "ACoAAAFq7eEBqcL8U1GE2pnsXDh5zDmbBT3e51Y",
        "distance": "DISTANCE_3",
        "public_id": "adriana-b-515b707",
        "tracking_id": "23784929"
    },
    {
        "urn_id": "ACoAAApCHxwBLDFHCyExsY2Z9cTVb7C-xEAr8Bc",
        "distance": "DISTANCE_3",
        "public_id": "leonardogarrido1",
        "tracking_id": "172105500"
    },
    {
        "urn_id": "ACoAAChKdZYB77mMDQ5jcetecHh2gFL_A-mp6I4",
        "distance": "DISTANCE_3",
        "public_id": "josé-sidjone-50646916a",
        "tracking_id": "675968406"
    },
    {
        "urn_id": "ACoAABWcVYkBEjxDxvQFe-bmNT0Nl6e-X2CJcuE",
        "distance": "DISTANCE_3",
        "public_id": "felipe-reis-a8950aa1",
        "tracking_id": "362567049"
    },
    {
        "urn_id": "ACoAABKDG7QBJ0y8TFGDVnBrGwE2yRhl5Qa-67E",
        "distance": "DISTANCE_3",
        "public_id": "diego-ramos-09801b88",
        "tracking_id": "310582196"
    },
    {
        "urn_id": "ACoAADVXqK0BX3GzXUV7g0bYP_d1oxOeIK9_URI",
        "distance": "DISTANCE_3",
        "public_id": "mirella-mirthes-61186720b",
        "tracking_id": "894937261"
    },
    {
        "urn_id": "ACoAADBEeZ0BrVy6qJbWXlPh7_IovwwFXwE_q4A",
        "distance": "DISTANCE_3",
        "public_id": "cleber-geraldo",
        "tracking_id": "809793949"
    },
    {
        "urn_id": "ACoAACzH5ZcBqc52NMvL2xOXEVr0hy-HjK79Ipo",
        "distance": "DISTANCE_3",
        "public_id": "ariadne-cruz-a9b73618b",
        "tracking_id": "751297943"
    },
    {
        "urn_id": "ACoAABexze4BDCOWSpB7leAUozCxai51f02Yp08",
        "distance": "DISTANCE_3",
        "public_id": "bruna-marçal-2ba16bb1",
        "tracking_id": "397528558"
    },
    {
        "urn_id": "ACoAACt1nvcBmX8ds3Q6kGmao7B7Dx4tjuV7P6E",
        "distance": "DISTANCE_3",
        "public_id": "josé-rivaldo-freitas-587225184",
        "tracking_id": "729128695"
    },
    {
        "urn_id": "ACoAACzOEjMBHOAKFE3U_aX6hbsdWMDAIqwiGWo",
        "distance": "DISTANCE_3",
        "public_id": "carla-marina-de-melo-moura-da-silva-0978b118b",
        "tracking_id": "751702579"
    },
    {
        "urn_id": "ACoAAArXpncBS4-rBFCLalmVrl_EtE7OhijzZ14",
        "distance": "DISTANCE_3",
        "public_id": "niedja-oliveira-nóbrega-133b0550",
        "tracking_id": "181905015"
    },
    {
        "urn_id": "ACoAAC--kwMBRADlCzfLSW9se96y7OQOOFha5PI",
        "distance": "DISTANCE_3",
        "public_id": "jonahttan-affonso-5433141a4",
        "tracking_id": "801018627"
    },
    {
        "urn_id": "ACoAAA9JnLoBux0knkwVtIEmbC1D1lpoBN6eg4w",
        "distance": "DISTANCE_3",
        "public_id": "dayanneferreira",
        "tracking_id": "256482490"
    },
    {
        "urn_id": "ACoAADI2wwQBoNir9ymg6yqRbDCvKf9svct7zJM",
        "distance": "DISTANCE_3",
        "public_id": "nicholas-wacherski-8b01741b6",
        "tracking_id": "842449668"
    },
    {
        "urn_id": "ACoAAA9ET98BbO9QzXrq1F558go94hlxV6yfu64",
        "distance": "DISTANCE_3",
        "public_id": "ederson-luis-hostim-42794271",
        "tracking_id": "256135135"
    },
    {
        "urn_id": "ACoAACx6XkoBat_Xuy1Cc6dm7O8wS2gYfIfBdUc",
        "distance": "DISTANCE_3",
        "public_id": "paloma-bahia-68aaa6189",
        "tracking_id": "746217034"
    },
    {
        "urn_id": "ACoAABEoUxgB7iV2h1Lqru9Qrea10EwRT5YDLWg",
        "distance": "DISTANCE_3",
        "public_id": "márcio-colares-b8849a80",
        "tracking_id": "287855384"
    },
    {
        "urn_id": "ACoAAAdDF-IBkHRbXykEK-KEtdipqaPCu2S57qk",
        "distance": "DISTANCE_3",
        "public_id": "marcel-siqueira-a0297734",
        "tracking_id": "121837538"
    },
    {
        "urn_id": "ACoAABS-_ZUBNueuONFiOftB4MUmMh78Kjt4r00",
        "distance": "DISTANCE_3",
        "public_id": "dilnei-tavares-29969498",
        "tracking_id": "348061077"
    },
    {
        "urn_id": "ACoAADLMDSoBSAwOyLFIdyBQr4Kix3P9svR9mis",
        "distance": "DISTANCE_3",
        "public_id": "lívia-hertel-8364b21b9",
        "tracking_id": "852233514"
    },
    {
        "urn_id": "ACoAADVf-OYB8FD9hqEzAVhJj5R8dUyN7N3Cbo0",
        "distance": "DISTANCE_3",
        "public_id": "jaques-alves-da-silva-972a8a20b",
        "tracking_id": "895482086"
    },
    {
        "urn_id": "ACoAABykJOUB69wiP1hrYGe3OuoeKZrQUeHs5ok",
        "distance": "DISTANCE_3",
        "public_id": "lucas-corujeira-daltro",
        "tracking_id": "480519397"
    },
    {
        "urn_id": "ACoAADLmpMEBlQJK2qA7VMrhXRZpl9WH8lhPC3U",
        "distance": "DISTANCE_3",
        "public_id": "luciano-alves-pereira-281bb31b9",
        "tracking_id": "853976257"
    }
]